{
  "_note": "DUMMY DATA - sketch only, not real MEN figures",
  "national": [
    {
      "ANO": 2011,
      "COBERTURA_NETA": 84.0,
      "DESERCION": 5.2,
      "REPITENCIA": 2.8,
      "REPROBACION": 2.8,
      "APROBACION": 91.0
    },
    {
      "ANO": 2012,
      "COBERTURA_NETA": 84.5,
      "DESERCION": 5.0,
      "REPITENCIA": 2.6,
      "REPROBACION": 3.0,
      "APROBACION": 91.5
    },
    {
      "ANO": 2013,
      "COBERTURA_NETA": 85.0,
      "DESERCION": 4.5,
      "REPITENCIA": 2.5,
      "REPROBACION": 3.2,
      "APROBACION": 92.0
    },
    {
      "ANO": 2014,
      "COBERTURA_NETA": 85.5,
      "DESERCION": 4.2,
      "REPITENCIA": 2.4,
      "REPROBACION": 2.8,
      "APROBACION": 92.5
    },
    {
      "ANO": 2015,
      "COBERTURA_NETA": 85.0,
      "DESERCION": 4.0,
      "REPITENCIA": 2.2,
      "REPROBACION": 4.0,
      "APROBACION": 90.0
    },
    {
      "ANO": 2016,
      "COBERTURA_NETA": 85.2,
      "DESERCION": 4.3,
      "REPITENCIA": 2.5,
      "REPROBACION": 3.8,
      "APROBACION": 90.5
    },
    {
      "ANO": 2017,
      "COBERTURA_NETA": 85.0,
      "DESERCION": 4.0,
      "REPITENCIA": 2.9,
      "REPROBACION": 4.1,
      "APROBACION": 90.5
    },
    {
      "ANO": 2018,
      "COBERTURA_NETA": 88.0,
      "DESERCION": 3.5,
      "REPITENCIA": 2.4,
      "REPROBACION": 4.5,
      "APROBACION": 90.0
    },
    {
      "ANO": 2019,
      "COBERTURA_NETA": 88.5,
      "DESERCION": 3.5,
      "REPITENCIA": 2.6,
      "REPROBACION": 4.8,
      "APROBACION": 90.0
    },
    {
      "ANO": 2020,
      "COBERTURA_NETA": 88.5,
      "DESERCION": 3.0,
      "REPITENCIA": 6.3,
      "REPROBACION": 5.0,
      "APROBACION": 89.0
    },
    {
      "ANO": 2021,
      "COBERTURA_NETA": 89.0,
      "DESERCION": 4.2,
      "REPITENCIA": 5.8,
      "REPROBACION": 5.5,
      "APROBACION": 87.5
    },
    {
      "ANO": 2022,
      "COBERTURA_NETA": 88.0,
      "DESERCION": 4.7,
      "REPITENCIA": 7.5,
      "REPROBACION": 5.8,
      "APROBACION": 87.5
    },
    {
      "ANO": 2023,
      "COBERTURA_NETA": 87.0,
      "DESERCION": 4.3,
      "REPITENCIA": 10.2,
      "REPROBACION": 6.0,
      "APROBACION": 88.0
    },
    {
      "ANO": 2024,
      "COBERTURA_NETA": 85.5,
      "DESERCION": 4.1,
      "REPITENCIA": 9.7,
      "REPROBACION": 5.8,
      "APROBACION": 88.5
    }
  ],
  "timeseries": [
    {
      "ANO": 2011,
      "DEPARTAMENTO": "Depto Norte",
      "COBERTURA_NETA": 90.4,
      "DESERCION": 3.53,
      "REPITENCIA": 2.66
    },
    {
      "ANO": 2011,
      "DEPARTAMENTO": "Depto Sur",
      "COBERTURA_NETA": 81.2,
      "DESERCION": 4.24,
      "REPITENCIA": 3.18
    },
    {
      "ANO": 2011,
      "DEPARTAMENTO": "Depto Este",
      "COBERTURA_NETA": 89.2,
      "DESERCION": 3.59,
      "REPITENCIA": 2.85
    },
    {
      "ANO": 2011,
      "DEPARTAMENTO": "Depto Oeste",
      "COBERTURA_NETA": 84.6,
      "DESERCION": 3.72,
      "REPITENCIA": 2.96
    },
    {
      "ANO": 2011,
      "DEPARTAMENTO": "Depto Centro",
      "COBERTURA_NETA": 89.6,
      "DESERCION": 3.7,
      "REPITENCIA": 3.14
    },
    {
      "ANO": 2011,
      "DEPARTAMENTO": "Depto Amazonia",
      "COBERTURA_NETA": 65.1,
      "DESERCION": 3.72,
      "REPITENCIA": 3.07
    },
    {
      "ANO": 2011,
      "DEPARTAMENTO": "Depto Caribe",
      "COBERTURA_NETA": 94.9,
      "DESERCION": 3.51,
      "REPITENCIA": 3.35
    },
    {
      "ANO": 2011,
      "DEPARTAMENTO": "Depto Pacífico",
      "COBERTURA_NETA": 75.6,
      "DESERCION": 3.84,
      "REPITENCIA": 2.5
    },
    {
      "ANO": 2011,
      "DEPARTAMENTO": "Depto Llanos",
      "COBERTURA_NETA": 79.4,
      "DESERCION": 3.84,
      "REPITENCIA": 2.42
    },
    {
      "ANO": 2011,
      "DEPARTAMENTO": "Depto Andino",
      "COBERTURA_NETA": 83.8,
      "DESERCION": 4.35,
      "REPITENCIA": 3.08
    },
    {
      "ANO": 2012,
      "DEPARTAMENTO": "Depto Norte",
      "COBERTURA_NETA": 91.0,
      "DESERCION": 4.2,
      "REPITENCIA": 2.8
    },
    {
      "ANO": 2012,
      "DEPARTAMENTO": "Depto Sur",
      "COBERTURA_NETA": 83.5,
      "DESERCION": 3.85,
      "REPITENCIA": 2.82
    },
    {
      "ANO": 2012,
      "DEPARTAMENTO": "Depto Este",
      "COBERTURA_NETA": 89.1,
      "DESERCION": 4.09,
      "REPITENCIA": 3.22
    },
    {
      "ANO": 2012,
      "DEPARTAMENTO": "Depto Oeste",
      "COBERTURA_NETA": 86.3,
      "DESERCION": 4.17,
      "REPITENCIA": 2.16
    },
    {
      "ANO": 2012,
      "DEPARTAMENTO": "Depto Centro",
      "COBERTURA_NETA": 90.3,
      "DESERCION": 3.76,
      "REPITENCIA": 2.2
    },
    {
      "ANO": 2012,
      "DEPARTAMENTO": "Depto Amazonia",
      "COBERTURA_NETA": 64.3,
      "DESERCION": 3.57,
      "REPITENCIA": 2.46
    },
    {
      "ANO": 2012,
      "DEPARTAMENTO": "Depto Caribe",
      "COBERTURA_NETA": 94.5,
      "DESERCION": 3.83,
      "REPITENCIA": 2.58
    },
    {
      "ANO": 2012,
      "DEPARTAMENTO": "Depto Pacífico",
      "COBERTURA_NETA": 74.2,
      "DESERCION": 3.74,
      "REPITENCIA": 3.32
    },
    {
      "ANO": 2012,
      "DEPARTAMENTO": "Depto Llanos",
      "COBERTURA_NETA": 78.5,
      "DESERCION": 4.08,
      "REPITENCIA": 2.32
    },
    {
      "ANO": 2012,
      "DEPARTAMENTO": "Depto Andino",
      "COBERTURA_NETA": 85.8,
      "DESERCION": 3.63,
      "REPITENCIA": 2.59
    },
    {
      "ANO": 2013,
      "DEPARTAMENTO": "Depto Norte",
      "COBERTURA_NETA": 91.7,
      "DESERCION": 4.08,
      "REPITENCIA": 2.72
    },
    {
      "ANO": 2013,
      "DEPARTAMENTO": "Depto Sur",
      "COBERTURA_NETA": 82.8,
      "DESERCION": 4.28,
      "REPITENCIA": 3.01
    },
    {
      "ANO": 2013,
      "DEPARTAMENTO": "Depto Este",
      "COBERTURA_NETA": 87.4,
      "DESERCION": 3.47,
      "REPITENCIA": 2.41
    },
    {
      "ANO": 2013,
      "DEPARTAMENTO": "Depto Oeste",
      "COBERTURA_NETA": 85.5,
      "DESERCION": 3.65,
      "REPITENCIA": 3.23
    },
    {
      "ANO": 2013,
      "DEPARTAMENTO": "Depto Centro",
      "COBERTURA_NETA": 92.3,
      "DESERCION": 3.75,
      "REPITENCIA": 2.85
    },
    {
      "ANO": 2013,
      "DEPARTAMENTO": "Depto Amazonia",
      "COBERTURA_NETA": 64.9,
      "DESERCION": 4.35,
      "REPITENCIA": 2.6
    },
    {
      "ANO": 2013,
      "DEPARTAMENTO": "Depto Caribe",
      "COBERTURA_NETA": 93.5,
      "DESERCION": 3.69,
      "REPITENCIA": 2.73
    },
    {
      "ANO": 2013,
      "DEPARTAMENTO": "Depto Pacífico",
      "COBERTURA_NETA": 74.5,
      "DESERCION": 4.02,
      "REPITENCIA": 3.17
    },
    {
      "ANO": 2013,
      "DEPARTAMENTO": "Depto Llanos",
      "COBERTURA_NETA": 77.9,
      "DESERCION": 3.66,
      "REPITENCIA": 3.3
    },
    {
      "ANO": 2013,
      "DEPARTAMENTO": "Depto Andino",
      "COBERTURA_NETA": 85.2,
      "DESERCION": 3.53,
      "REPITENCIA": 2.06
    },
    {
      "ANO": 2014,
      "DEPARTAMENTO": "Depto Norte",
      "COBERTURA_NETA": 89.1,
      "DESERCION": 4.04,
      "REPITENCIA": 2.93
    },
    {
      "ANO": 2014,
      "DEPARTAMENTO": "Depto Sur",
      "COBERTURA_NETA": 82.1,
      "DESERCION": 3.47,
      "REPITENCIA": 2.4
    },
    {
      "ANO": 2014,
      "DEPARTAMENTO": "Depto Este",
      "COBERTURA_NETA": 89.8,
      "DESERCION": 3.94,
      "REPITENCIA": 3.16
    },
    {
      "ANO": 2014,
      "DEPARTAMENTO": "Depto Oeste",
      "COBERTURA_NETA": 87.4,
      "DESERCION": 3.42,
      "REPITENCIA": 2.84
    },
    {
      "ANO": 2014,
      "DEPARTAMENTO": "Depto Centro",
      "COBERTURA_NETA": 91.8,
      "DESERCION": 3.95,
      "REPITENCIA": 2.25
    },
    {
      "ANO": 2014,
      "DEPARTAMENTO": "Depto Amazonia",
      "COBERTURA_NETA": 65.7,
      "DESERCION": 3.52,
      "REPITENCIA": 2.47
    },
    {
      "ANO": 2014,
      "DEPARTAMENTO": "Depto Caribe",
      "COBERTURA_NETA": 94.2,
      "DESERCION": 4.36,
      "REPITENCIA": 3.04
    },
    {
      "ANO": 2014,
      "DEPARTAMENTO": "Depto Pacífico",
      "COBERTURA_NETA": 74.6,
      "DESERCION": 3.91,
      "REPITENCIA": 2.13
    },
    {
      "ANO": 2014,
      "DEPARTAMENTO": "Depto Llanos",
      "COBERTURA_NETA": 79.5,
      "DESERCION": 4.28,
      "REPITENCIA": 2.29
    },
    {
      "ANO": 2014,
      "DEPARTAMENTO": "Depto Andino",
      "COBERTURA_NETA": 85.7,
      "DESERCION": 4.02,
      "REPITENCIA": 2.1
    },
    {
      "ANO": 2015,
      "DEPARTAMENTO": "Depto Norte",
      "COBERTURA_NETA": 91.2,
      "DESERCION": 3.92,
      "REPITENCIA": 2.71
    },
    {
      "ANO": 2015,
      "DEPARTAMENTO": "Depto Sur",
      "COBERTURA_NETA": 82.5,
      "DESERCION": 3.38,
      "REPITENCIA": 2.12
    },
    {
      "ANO": 2015,
      "DEPARTAMENTO": "Depto Este",
      "COBERTURA_NETA": 87.0,
      "DESERCION": 4.31,
      "REPITENCIA": 2.84
    },
    {
      "ANO": 2015,
      "DEPARTAMENTO": "Depto Oeste",
      "COBERTURA_NETA": 87.4,
      "DESERCION": 3.69,
      "REPITENCIA": 1.78
    },
    {
      "ANO": 2015,
      "DEPARTAMENTO": "Depto Centro",
      "COBERTURA_NETA": 92.5,
      "DESERCION": 4.33,
      "REPITENCIA": 1.81
    },
    {
      "ANO": 2015,
      "DEPARTAMENTO": "Depto Amazonia",
      "COBERTURA_NETA": 65.4,
      "DESERCION": 3.45,
      "REPITENCIA": 2.69
    },
    {
      "ANO": 2015,
      "DEPARTAMENTO": "Depto Caribe",
      "COBERTURA_NETA": 95.2,
      "DESERCION": 3.51,
      "REPITENCIA": 2.32
    },
    {
      "ANO": 2015,
      "DEPARTAMENTO": "Depto Pacífico",
      "COBERTURA_NETA": 75.5,
      "DESERCION": 3.65,
      "REPITENCIA": 2.83
    },
    {
      "ANO": 2015,
      "DEPARTAMENTO": "Depto Llanos",
      "COBERTURA_NETA": 78.2,
      "DESERCION": 3.59,
      "REPITENCIA": 2.4
    },
    {
      "ANO": 2015,
      "DEPARTAMENTO": "Depto Andino",
      "COBERTURA_NETA": 86.1,
      "DESERCION": 3.58,
      "REPITENCIA": 2.11
    },
    {
      "ANO": 2016,
      "DEPARTAMENTO": "Depto Norte",
      "COBERTURA_NETA": 92.0,
      "DESERCION": 4.0,
      "REPITENCIA": 2.57
    },
    {
      "ANO": 2016,
      "DEPARTAMENTO": "Depto Sur",
      "COBERTURA_NETA": 82.6,
      "DESERCION": 3.47,
      "REPITENCIA": 2.29
    },
    {
      "ANO": 2016,
      "DEPARTAMENTO": "Depto Este",
      "COBERTURA_NETA": 88.0,
      "DESERCION": 3.94,
      "REPITENCIA": 2.3
    },
    {
      "ANO": 2016,
      "DEPARTAMENTO": "Depto Oeste",
      "COBERTURA_NETA": 85.7,
      "DESERCION": 3.42,
      "REPITENCIA": 2.82
    },
    {
      "ANO": 2016,
      "DEPARTAMENTO": "Depto Centro",
      "COBERTURA_NETA": 90.7,
      "DESERCION": 4.26,
      "REPITENCIA": 3.12
    },
    {
      "ANO": 2016,
      "DEPARTAMENTO": "Depto Amazonia",
      "COBERTURA_NETA": 64.2,
      "DESERCION": 3.59,
      "REPITENCIA": 2.87
    },
    {
      "ANO": 2016,
      "DEPARTAMENTO": "Depto Caribe",
      "COBERTURA_NETA": 93.6,
      "DESERCION": 3.48,
      "REPITENCIA": 3.22
    },
    {
      "ANO": 2016,
      "DEPARTAMENTO": "Depto Pacífico",
      "COBERTURA_NETA": 75.7,
      "DESERCION": 3.82,
      "REPITENCIA": 3.02
    },
    {
      "ANO": 2016,
      "DEPARTAMENTO": "Depto Llanos",
      "COBERTURA_NETA": 79.4,
      "DESERCION": 3.54,
      "REPITENCIA": 2.13
    },
    {
      "ANO": 2016,
      "DEPARTAMENTO": "Depto Andino",
      "COBERTURA_NETA": 85.3,
      "DESERCION": 3.77,
      "REPITENCIA": 2.61
    },
    {
      "ANO": 2017,
      "DEPARTAMENTO": "Depto Norte",
      "COBERTURA_NETA": 91.3,
      "DESERCION": 3.99,
      "REPITENCIA": 3.68
    },
    {
      "ANO": 2017,
      "DEPARTAMENTO": "Depto Sur",
      "COBERTURA_NETA": 81.4,
      "DESERCION": 3.72,
      "REPITENCIA": 2.84
    },
    {
      "ANO": 2017,
      "DEPARTAMENTO": "Depto Este",
      "COBERTURA_NETA": 89.7,
      "DESERCION": 3.57,
      "REPITENCIA": 2.65
    },
    {
      "ANO": 2017,
      "DEPARTAMENTO": "Depto Oeste",
      "COBERTURA_NETA": 86.4,
      "DESERCION": 3.74,
      "REPITENCIA": 2.76
    },
    {
      "ANO": 2017,
      "DEPARTAMENTO": "Depto Centro",
      "COBERTURA_NETA": 90.8,
      "DESERCION": 4.24,
      "REPITENCIA": 2.98
    },
    {
      "ANO": 2017,
      "DEPARTAMENTO": "Depto Amazonia",
      "COBERTURA_NETA": 66.7,
      "DESERCION": 3.87,
      "REPITENCIA": 2.47
    },
    {
      "ANO": 2017,
      "DEPARTAMENTO": "Depto Caribe",
      "COBERTURA_NETA": 96.1,
      "DESERCION": 4.16,
      "REPITENCIA": 3.66
    },
    {
      "ANO": 2017,
      "DEPARTAMENTO": "Depto Pacífico",
      "COBERTURA_NETA": 76.9,
      "DESERCION": 4.17,
      "REPITENCIA": 2.62
    },
    {
      "ANO": 2017,
      "DEPARTAMENTO": "Depto Llanos",
      "COBERTURA_NETA": 78.6,
      "DESERCION": 3.53,
      "REPITENCIA": 2.92
    },
    {
      "ANO": 2017,
      "DEPARTAMENTO": "Depto Andino",
      "COBERTURA_NETA": 84.3,
      "DESERCION": 3.7,
      "REPITENCIA": 3.68
    },
    {
      "ANO": 2018,
      "DEPARTAMENTO": "Depto Norte",
      "COBERTURA_NETA": 90.0,
      "DESERCION": 4.07,
      "REPITENCIA": 2.49
    },
    {
      "ANO": 2018,
      "DEPARTAMENTO": "Depto Sur",
      "COBERTURA_NETA": 82.5,
      "DESERCION": 4.25,
      "REPITENCIA": 3.19
    },
    {
      "ANO": 2018,
      "DEPARTAMENTO": "Depto Este",
      "COBERTURA_NETA": 88.9,
      "DESERCION": 4.01,
      "REPITENCIA": 2.1
    },
    {
      "ANO": 2018,
      "DEPARTAMENTO": "Depto Oeste",
      "COBERTURA_NETA": 86.1,
      "DESERCION": 4.26,
      "REPITENCIA": 2.65
    },
    {
      "ANO": 2018,
      "DEPARTAMENTO": "Depto Centro",
      "COBERTURA_NETA": 91.8,
      "DESERCION": 4.04,
      "REPITENCIA": 1.97
    },
    {
      "ANO": 2018,
      "DEPARTAMENTO": "Depto Amazonia",
      "COBERTURA_NETA": 66.0,
      "DESERCION": 3.79,
      "REPITENCIA": 3.01
    },
    {
      "ANO": 2018,
      "DEPARTAMENTO": "Depto Caribe",
      "COBERTURA_NETA": 93.7,
      "DESERCION": 4.25,
      "REPITENCIA": 2.0
    },
    {
      "ANO": 2018,
      "DEPARTAMENTO": "Depto Pacífico",
      "COBERTURA_NETA": 74.8,
      "DESERCION": 3.89,
      "REPITENCIA": 2.78
    },
    {
      "ANO": 2018,
      "DEPARTAMENTO": "Depto Llanos",
      "COBERTURA_NETA": 77.9,
      "DESERCION": 3.41,
      "REPITENCIA": 3.06
    },
    {
      "ANO": 2018,
      "DEPARTAMENTO": "Depto Andino",
      "COBERTURA_NETA": 84.9,
      "DESERCION": 3.88,
      "REPITENCIA": 2.71
    },
    {
      "ANO": 2019,
      "DEPARTAMENTO": "Depto Norte",
      "COBERTURA_NETA": 90.6,
      "DESERCION": 3.84,
      "REPITENCIA": 2.78
    },
    {
      "ANO": 2019,
      "DEPARTAMENTO": "Depto Sur",
      "COBERTURA_NETA": 84.1,
      "DESERCION": 3.46,
      "REPITENCIA": 3.03
    },
    {
      "ANO": 2019,
      "DEPARTAMENTO": "Depto Este",
      "COBERTURA_NETA": 88.0,
      "DESERCION": 3.66,
      "REPITENCIA": 2.97
    },
    {
      "ANO": 2019,
      "DEPARTAMENTO": "Depto Oeste",
      "COBERTURA_NETA": 86.2,
      "DESERCION": 3.58,
      "REPITENCIA": 3.08
    },
    {
      "ANO": 2019,
      "DEPARTAMENTO": "Depto Centro",
      "COBERTURA_NETA": 90.5,
      "DESERCION": 3.72,
      "REPITENCIA": 3.4
    },
    {
      "ANO": 2019,
      "DEPARTAMENTO": "Depto Amazonia",
      "COBERTURA_NETA": 67.3,
      "DESERCION": 3.33,
      "REPITENCIA": 2.38
    },
    {
      "ANO": 2019,
      "DEPARTAMENTO": "Depto Caribe",
      "COBERTURA_NETA": 94.1,
      "DESERCION": 4.19,
      "REPITENCIA": 3.25
    },
    {
      "ANO": 2019,
      "DEPARTAMENTO": "Depto Pacífico",
      "COBERTURA_NETA": 76.9,
      "DESERCION": 3.63,
      "REPITENCIA": 2.31
    },
    {
      "ANO": 2019,
      "DEPARTAMENTO": "Depto Llanos",
      "COBERTURA_NETA": 79.8,
      "DESERCION": 3.96,
      "REPITENCIA": 2.9
    },
    {
      "ANO": 2019,
      "DEPARTAMENTO": "Depto Andino",
      "COBERTURA_NETA": 87.3,
      "DESERCION": 3.91,
      "REPITENCIA": 2.11
    },
    {
      "ANO": 2020,
      "DEPARTAMENTO": "Depto Norte",
      "COBERTURA_NETA": 91.9,
      "DESERCION": 3.53,
      "REPITENCIA": 6.66
    },
    {
      "ANO": 2020,
      "DEPARTAMENTO": "Depto Sur",
      "COBERTURA_NETA": 84.2,
      "DESERCION": 3.36,
      "REPITENCIA": 5.95
    },
    {
      "ANO": 2020,
      "DEPARTAMENTO": "Depto Este",
      "COBERTURA_NETA": 87.7,
      "DESERCION": 3.78,
      "REPITENCIA": 6.15
    },
    {
      "ANO": 2020,
      "DEPARTAMENTO": "Depto Oeste",
      "COBERTURA_NETA": 87.2,
      "DESERCION": 3.95,
      "REPITENCIA": 6.06
    },
    {
      "ANO": 2020,
      "DEPARTAMENTO": "Depto Centro",
      "COBERTURA_NETA": 92.3,
      "DESERCION": 3.49,
      "REPITENCIA": 6.44
    },
    {
      "ANO": 2020,
      "DEPARTAMENTO": "Depto Amazonia",
      "COBERTURA_NETA": 67.1,
      "DESERCION": 4.08,
      "REPITENCIA": 5.92
    },
    {
      "ANO": 2020,
      "DEPARTAMENTO": "Depto Caribe",
      "COBERTURA_NETA": 94.7,
      "DESERCION": 3.51,
      "REPITENCIA": 5.8
    },
    {
      "ANO": 2020,
      "DEPARTAMENTO": "Depto Pacífico",
      "COBERTURA_NETA": 76.7,
      "DESERCION": 3.87,
      "REPITENCIA": 6.14
    },
    {
      "ANO": 2020,
      "DEPARTAMENTO": "Depto Llanos",
      "COBERTURA_NETA": 79.6,
      "DESERCION": 3.78,
      "REPITENCIA": 6.36
    },
    {
      "ANO": 2020,
      "DEPARTAMENTO": "Depto Andino",
      "COBERTURA_NETA": 84.4,
      "DESERCION": 3.31,
      "REPITENCIA": 6.95
    },
    {
      "ANO": 2021,
      "DEPARTAMENTO": "Depto Norte",
      "COBERTURA_NETA": 92.2,
      "DESERCION": 3.75,
      "REPITENCIA": 6.38
    },
    {
      "ANO": 2021,
      "DEPARTAMENTO": "Depto Sur",
      "COBERTURA_NETA": 83.2,
      "DESERCION": 3.35,
      "REPITENCIA": 5.47
    },
    {
      "ANO": 2021,
      "DEPARTAMENTO": "Depto Este",
      "COBERTURA_NETA": 88.4,
      "DESERCION": 4.1,
      "REPITENCIA": 6.33
    },
    {
      "ANO": 2021,
      "DEPARTAMENTO": "Depto Oeste",
      "COBERTURA_NETA": 88.1,
      "DESERCION": 4.1,
      "REPITENCIA": 5.57
    },
    {
      "ANO": 2021,
      "DEPARTAMENTO": "Depto Centro",
      "COBERTURA_NETA": 91.2,
      "DESERCION": 3.3,
      "REPITENCIA": 6.31
    },
    {
      "ANO": 2021,
      "DEPARTAMENTO": "Depto Amazonia",
      "COBERTURA_NETA": 67.2,
      "DESERCION": 3.61,
      "REPITENCIA": 6.11
    },
    {
      "ANO": 2021,
      "DEPARTAMENTO": "Depto Caribe",
      "COBERTURA_NETA": 94.0,
      "DESERCION": 4.13,
      "REPITENCIA": 6.42
    },
    {
      "ANO": 2021,
      "DEPARTAMENTO": "Depto Pacífico",
      "COBERTURA_NETA": 77.4,
      "DESERCION": 4.01,
      "REPITENCIA": 6.45
    },
    {
      "ANO": 2021,
      "DEPARTAMENTO": "Depto Llanos",
      "COBERTURA_NETA": 77.6,
      "DESERCION": 3.94,
      "REPITENCIA": 5.73
    },
    {
      "ANO": 2021,
      "DEPARTAMENTO": "Depto Andino",
      "COBERTURA_NETA": 87.3,
      "DESERCION": 4.0,
      "REPITENCIA": 6.42
    },
    {
      "ANO": 2022,
      "DEPARTAMENTO": "Depto Norte",
      "COBERTURA_NETA": 92.0,
      "DESERCION": 3.44,
      "REPITENCIA": 8.02
    },
    {
      "ANO": 2022,
      "DEPARTAMENTO": "Depto Sur",
      "COBERTURA_NETA": 81.9,
      "DESERCION": 4.04,
      "REPITENCIA": 8.12
    },
    {
      "ANO": 2022,
      "DEPARTAMENTO": "Depto Este",
      "COBERTURA_NETA": 88.3,
      "DESERCION": 3.99,
      "REPITENCIA": 7.6
    },
    {
      "ANO": 2022,
      "DEPARTAMENTO": "Depto Oeste",
      "COBERTURA_NETA": 86.5,
      "DESERCION": 3.97,
      "REPITENCIA": 7.3
    },
    {
      "ANO": 2022,
      "DEPARTAMENTO": "Depto Centro",
      "COBERTURA_NETA": 90.7,
      "DESERCION": 3.36,
      "REPITENCIA": 7.43
    },
    {
      "ANO": 2022,
      "DEPARTAMENTO": "Depto Amazonia",
      "COBERTURA_NETA": 67.2,
      "DESERCION": 4.14,
      "REPITENCIA": 7.36
    },
    {
      "ANO": 2022,
      "DEPARTAMENTO": "Depto Caribe",
      "COBERTURA_NETA": 95.5,
      "DESERCION": 3.57,
      "REPITENCIA": 8.28
    },
    {
      "ANO": 2022,
      "DEPARTAMENTO": "Depto Pacífico",
      "COBERTURA_NETA": 76.2,
      "DESERCION": 4.11,
      "REPITENCIA": 7.15
    },
    {
      "ANO": 2022,
      "DEPARTAMENTO": "Depto Llanos",
      "COBERTURA_NETA": 80.5,
      "DESERCION": 3.35,
      "REPITENCIA": 8.25
    },
    {
      "ANO": 2022,
      "DEPARTAMENTO": "Depto Andino",
      "COBERTURA_NETA": 85.4,
      "DESERCION": 3.28,
      "REPITENCIA": 7.56
    },
    {
      "ANO": 2023,
      "DEPARTAMENTO": "Depto Norte",
      "COBERTURA_NETA": 91.9,
      "DESERCION": 3.45,
      "REPITENCIA": 10.49
    },
    {
      "ANO": 2023,
      "DEPARTAMENTO": "Depto Sur",
      "COBERTURA_NETA": 83.2,
      "DESERCION": 3.53,
      "REPITENCIA": 10.45
    },
    {
      "ANO": 2023,
      "DEPARTAMENTO": "Depto Este",
      "COBERTURA_NETA": 88.5,
      "DESERCION": 3.85,
      "REPITENCIA": 9.7
    },
    {
      "ANO": 2023,
      "DEPARTAMENTO": "Depto Oeste",
      "COBERTURA_NETA": 88.5,
      "DESERCION": 3.68,
      "REPITENCIA": 10.64
    },
    {
      "ANO": 2023,
      "DEPARTAMENTO": "Depto Centro",
      "COBERTURA_NETA": 92.9,
      "DESERCION": 3.81,
      "REPITENCIA": 10.17
    },
    {
      "ANO": 2023,
      "DEPARTAMENTO": "Depto Amazonia",
      "COBERTURA_NETA": 64.9,
      "DESERCION": 3.8,
      "REPITENCIA": 10.13
    },
    {
      "ANO": 2023,
      "DEPARTAMENTO": "Depto Caribe",
      "COBERTURA_NETA": 94.6,
      "DESERCION": 3.99,
      "REPITENCIA": 10.64
    },
    {
      "ANO": 2023,
      "DEPARTAMENTO": "Depto Pacífico",
      "COBERTURA_NETA": 75.6,
      "DESERCION": 3.45,
      "REPITENCIA": 10.23
    },
    {
      "ANO": 2023,
      "DEPARTAMENTO": "Depto Llanos",
      "COBERTURA_NETA": 78.9,
      "DESERCION": 3.44,
      "REPITENCIA": 9.87
    },
    {
      "ANO": 2023,
      "DEPARTAMENTO": "Depto Andino",
      "COBERTURA_NETA": 86.0,
      "DESERCION": 4.08,
      "REPITENCIA": 10.58
    },
    {
      "ANO": 2024,
      "DEPARTAMENTO": "Depto Norte",
      "COBERTURA_NETA": 92.5,
      "DESERCION": 3.73,
      "REPITENCIA": 9.59
    },
    {
      "ANO": 2024,
      "DEPARTAMENTO": "Depto Sur",
      "COBERTURA_NETA": 83.4,
      "DESERCION": 3.11,
      "REPITENCIA": 9.57
    },
    {
      "ANO": 2024,
      "DEPARTAMENTO": "Depto Este",
      "COBERTURA_NETA": 89.1,
      "DESERCION": 3.69,
      "REPITENCIA": 10.05
    },
    {
      "ANO": 2024,
      "DEPARTAMENTO": "Depto Oeste",
      "COBERTURA_NETA": 87.2,
      "DESERCION": 3.55,
      "REPITENCIA": 9.48
    },
    {
      "ANO": 2024,
      "DEPARTAMENTO": "Depto Centro",
      "COBERTURA_NETA": 92.2,
      "DESERCION": 4.01,
      "REPITENCIA": 10.23
    },
    {
      "ANO": 2024,
      "DEPARTAMENTO": "Depto Amazonia",
      "COBERTURA_NETA": 65.3,
      "DESERCION": 3.19,
      "REPITENCIA": 9.87
    },
    {
      "ANO": 2024,
      "DEPARTAMENTO": "Depto Caribe",
      "COBERTURA_NETA": 95.7,
      "DESERCION": 3.45,
      "REPITENCIA": 10.26
    },
    {
      "ANO": 2024,
      "DEPARTAMENTO": "Depto Pacífico",
      "COBERTURA_NETA": 77.1,
      "DESERCION": 3.78,
      "REPITENCIA": 9.49
    },
    {
      "ANO": 2024,
      "DEPARTAMENTO": "Depto Llanos",
      "COBERTURA_NETA": 78.4,
      "DESERCION": 3.13,
      "REPITENCIA": 9.52
    },
    {
      "ANO": 2024,
      "DEPARTAMENTO": "Depto Andino",
      "COBERTURA_NETA": 86.2,
      "DESERCION": 3.96,
      "REPITENCIA": 9.29
    }
  ],
  "all": [
    {
      "ANO": 2011,
      "DEPARTAMENTO": "Departamento A",
      "COBERTURA_NETA": 54.8,
      "DESERCION": 5.51,
      "REPITENCIA": 2.59
    },
    {
      "ANO": 2011,
      "DEPARTAMENTO": "Departamento B",
      "COBERTURA_NETA": 56.8,
      "DESERCION": 5.19,
      "REPITENCIA": 2.67
    },
    {
      "ANO": 2011,
      "DEPARTAMENTO": "Departamento C",
      "COBERTURA_NETA": 58.1,
      "DESERCION": 4.01,
      "REPITENCIA": 3.43
    },
    {
      "ANO": 2011,
      "DEPARTAMENTO": "Departamento D",
      "COBERTURA_NETA": 59.7,
      "DESERCION": 4.26,
      "REPITENCIA": 2.94
    },
    {
      "ANO": 2011,
      "DEPARTAMENTO": "Departamento E",
      "COBERTURA_NETA": 60.0,
      "DESERCION": 6.3,
      "REPITENCIA": 3.08
    },
    {
      "ANO": 2011,
      "DEPARTAMENTO": "Departamento F",
      "COBERTURA_NETA": 61.1,
      "DESERCION": 4.6,
      "REPITENCIA": 3.57
    },
    {
      "ANO": 2011,
      "DEPARTAMENTO": "Departamento G",
      "COBERTURA_NETA": 63.3,
      "DESERCION": 5.92,
      "REPITENCIA": 3.3
    },
    {
      "ANO": 2011,
      "DEPARTAMENTO": "Departamento H",
      "COBERTURA_NETA": 65.8,
      "DESERCION": 5.43,
      "REPITENCIA": 3.73
    },
    {
      "ANO": 2011,
      "DEPARTAMENTO": "Departamento I",
      "COBERTURA_NETA": 67.0,
      "DESERCION": 5.47,
      "REPITENCIA": 3.38
    },
    {
      "ANO": 2011,
      "DEPARTAMENTO": "Departamento J",
      "COBERTURA_NETA": 67.6,
      "DESERCION": 5.99,
      "REPITENCIA": 3.12
    },
    {
      "ANO": 2011,
      "DEPARTAMENTO": "Departamento K",
      "COBERTURA_NETA": 69.8,
      "DESERCION": 5.78,
      "REPITENCIA": 3.01
    },
    {
      "ANO": 2011,
      "DEPARTAMENTO": "Departamento L",
      "COBERTURA_NETA": 69.9,
      "DESERCION": 4.59,
      "REPITENCIA": 3.26
    },
    {
      "ANO": 2011,
      "DEPARTAMENTO": "Departamento M",
      "COBERTURA_NETA": 72.3,
      "DESERCION": 5.25,
      "REPITENCIA": 3.24
    },
    {
      "ANO": 2011,
      "DEPARTAMENTO": "Departamento N",
      "COBERTURA_NETA": 72.7,
      "DESERCION": 4.19,
      "REPITENCIA": 2.73
    },
    {
      "ANO": 2011,
      "DEPARTAMENTO": "Departamento O",
      "COBERTURA_NETA": 74.1,
      "DESERCION": 4.77,
      "REPITENCIA": 3.11
    },
    {
      "ANO": 2011,
      "DEPARTAMENTO": "Departamento P",
      "COBERTURA_NETA": 75.3,
      "DESERCION": 4.56,
      "REPITENCIA": 3.34
    },
    {
      "ANO": 2011,
      "DEPARTAMENTO": "Departamento Q",
      "COBERTURA_NETA": 77.8,
      "DESERCION": 4.15,
      "REPITENCIA": 2.91
    },
    {
      "ANO": 2011,
      "DEPARTAMENTO": "Departamento R",
      "COBERTURA_NETA": 78.9,
      "DESERCION": 5.0,
      "REPITENCIA": 2.61
    },
    {
      "ANO": 2011,
      "DEPARTAMENTO": "Departamento S",
      "COBERTURA_NETA": 80.0,
      "DESERCION": 6.17,
      "REPITENCIA": 3.18
    },
    {
      "ANO": 2011,
      "DEPARTAMENTO": "Departamento T",
      "COBERTURA_NETA": 82.0,
      "DESERCION": 6.06,
      "REPITENCIA": 3.45
    },
    {
      "ANO": 2011,
      "DEPARTAMENTO": "Departamento U",
      "COBERTURA_NETA": 82.8,
      "DESERCION": 4.01,
      "REPITENCIA": 2.83
    },
    {
      "ANO": 2011,
      "DEPARTAMENTO": "Departamento V",
      "COBERTURA_NETA": 84.9,
      "DESERCION": 6.05,
      "REPITENCIA": 3.73
    },
    {
      "ANO": 2011,
      "DEPARTAMENTO": "Departamento W",
      "COBERTURA_NETA": 85.6,
      "DESERCION": 5.79,
      "REPITENCIA": 3.12
    },
    {
      "ANO": 2011,
      "DEPARTAMENTO": "Departamento X",
      "COBERTURA_NETA": 87.4,
      "DESERCION": 4.53,
      "REPITENCIA": 2.63
    },
    {
      "ANO": 2011,
      "DEPARTAMENTO": "Departamento Y",
      "COBERTURA_NETA": 88.5,
      "DESERCION": 4.07,
      "REPITENCIA": 2.8
    },
    {
      "ANO": 2011,
      "DEPARTAMENTO": "Departamento Z",
      "COBERTURA_NETA": 90.4,
      "DESERCION": 4.97,
      "REPITENCIA": 2.55
    },
    {
      "ANO": 2011,
      "DEPARTAMENTO": "Departamento [",
      "COBERTURA_NETA": 91.3,
      "DESERCION": 4.31,
      "REPITENCIA": 3.23
    },
    {
      "ANO": 2011,
      "DEPARTAMENTO": "Departamento \\",
      "COBERTURA_NETA": 91.9,
      "DESERCION": 4.95,
      "REPITENCIA": 3.15
    },
    {
      "ANO": 2011,
      "DEPARTAMENTO": "Departamento ]",
      "COBERTURA_NETA": 93.3,
      "DESERCION": 5.54,
      "REPITENCIA": 2.5
    },
    {
      "ANO": 2011,
      "DEPARTAMENTO": "Departamento ^",
      "COBERTURA_NETA": 95.5,
      "DESERCION": 4.12,
      "REPITENCIA": 2.87
    },
    {
      "ANO": 2011,
      "DEPARTAMENTO": "Departamento _",
      "COBERTURA_NETA": 96.4,
      "DESERCION": 4.78,
      "REPITENCIA": 3.44
    },
    {
      "ANO": 2011,
      "DEPARTAMENTO": "Departamento `",
      "COBERTURA_NETA": 98.2,
      "DESERCION": 5.8,
      "REPITENCIA": 3.55
    },
    {
      "ANO": 2011,
      "DEPARTAMENTO": "Departamento a",
      "COBERTURA_NETA": 99.3,
      "DESERCION": 4.2,
      "REPITENCIA": 2.33
    },
    {
      "ANO": 2012,
      "DEPARTAMENTO": "Departamento A",
      "COBERTURA_NETA": 55.2,
      "DESERCION": 6.2,
      "REPITENCIA": 2.62
    },
    {
      "ANO": 2012,
      "DEPARTAMENTO": "Departamento B",
      "COBERTURA_NETA": 56.8,
      "DESERCION": 5.67,
      "REPITENCIA": 3.08
    },
    {
      "ANO": 2012,
      "DEPARTAMENTO": "Departamento C",
      "COBERTURA_NETA": 58.4,
      "DESERCION": 6.08,
      "REPITENCIA": 2.4
    },
    {
      "ANO": 2012,
      "DEPARTAMENTO": "Departamento D",
      "COBERTURA_NETA": 58.3,
      "DESERCION": 4.17,
      "REPITENCIA": 2.29
    },
    {
      "ANO": 2012,
      "DEPARTAMENTO": "Departamento E",
      "COBERTURA_NETA": 61.0,
      "DESERCION": 5.15,
      "REPITENCIA": 2.43
    },
    {
      "ANO": 2012,
      "DEPARTAMENTO": "Departamento F",
      "COBERTURA_NETA": 62.5,
      "DESERCION": 5.64,
      "REPITENCIA": 2.35
    },
    {
      "ANO": 2012,
      "DEPARTAMENTO": "Departamento G",
      "COBERTURA_NETA": 63.7,
      "DESERCION": 5.6,
      "REPITENCIA": 2.27
    },
    {
      "ANO": 2012,
      "DEPARTAMENTO": "Departamento H",
      "COBERTURA_NETA": 65.5,
      "DESERCION": 6.12,
      "REPITENCIA": 2.26
    },
    {
      "ANO": 2012,
      "DEPARTAMENTO": "Departamento I",
      "COBERTURA_NETA": 65.3,
      "DESERCION": 4.55,
      "REPITENCIA": 3.12
    },
    {
      "ANO": 2012,
      "DEPARTAMENTO": "Departamento J",
      "COBERTURA_NETA": 68.6,
      "DESERCION": 4.75,
      "REPITENCIA": 3.17
    },
    {
      "ANO": 2012,
      "DEPARTAMENTO": "Departamento K",
      "COBERTURA_NETA": 68.2,
      "DESERCION": 5.46,
      "REPITENCIA": 3.04
    },
    {
      "ANO": 2012,
      "DEPARTAMENTO": "Departamento L",
      "COBERTURA_NETA": 69.7,
      "DESERCION": 5.65,
      "REPITENCIA": 3.38
    },
    {
      "ANO": 2012,
      "DEPARTAMENTO": "Departamento M",
      "COBERTURA_NETA": 72.1,
      "DESERCION": 4.09,
      "REPITENCIA": 3.58
    },
    {
      "ANO": 2012,
      "DEPARTAMENTO": "Departamento N",
      "COBERTURA_NETA": 73.8,
      "DESERCION": 4.63,
      "REPITENCIA": 2.74
    },
    {
      "ANO": 2012,
      "DEPARTAMENTO": "Departamento O",
      "COBERTURA_NETA": 74.4,
      "DESERCION": 5.01,
      "REPITENCIA": 2.61
    },
    {
      "ANO": 2012,
      "DEPARTAMENTO": "Departamento P",
      "COBERTURA_NETA": 76.8,
      "DESERCION": 5.77,
      "REPITENCIA": 2.26
    },
    {
      "ANO": 2012,
      "DEPARTAMENTO": "Departamento Q",
      "COBERTURA_NETA": 78.4,
      "DESERCION": 5.33,
      "REPITENCIA": 3.34
    },
    {
      "ANO": 2012,
      "DEPARTAMENTO": "Departamento R",
      "COBERTURA_NETA": 79.3,
      "DESERCION": 4.85,
      "REPITENCIA": 3.2
    },
    {
      "ANO": 2012,
      "DEPARTAMENTO": "Departamento S",
      "COBERTURA_NETA": 81.2,
      "DESERCION": 4.45,
      "REPITENCIA": 3.31
    },
    {
      "ANO": 2012,
      "DEPARTAMENTO": "Departamento T",
      "COBERTURA_NETA": 81.8,
      "DESERCION": 4.96,
      "REPITENCIA": 2.75
    },
    {
      "ANO": 2012,
      "DEPARTAMENTO": "Departamento U",
      "COBERTURA_NETA": 83.5,
      "DESERCION": 4.44,
      "REPITENCIA": 3.38
    },
    {
      "ANO": 2012,
      "DEPARTAMENTO": "Departamento V",
      "COBERTURA_NETA": 85.1,
      "DESERCION": 4.01,
      "REPITENCIA": 3.42
    },
    {
      "ANO": 2012,
      "DEPARTAMENTO": "Departamento W",
      "COBERTURA_NETA": 85.4,
      "DESERCION": 4.92,
      "REPITENCIA": 3.02
    },
    {
      "ANO": 2012,
      "DEPARTAMENTO": "Departamento X",
      "COBERTURA_NETA": 87.0,
      "DESERCION": 3.87,
      "REPITENCIA": 3.38
    },
    {
      "ANO": 2012,
      "DEPARTAMENTO": "Departamento Y",
      "COBERTURA_NETA": 88.0,
      "DESERCION": 4.31,
      "REPITENCIA": 3.3
    },
    {
      "ANO": 2012,
      "DEPARTAMENTO": "Departamento Z",
      "COBERTURA_NETA": 89.8,
      "DESERCION": 5.91,
      "REPITENCIA": 3.15
    },
    {
      "ANO": 2012,
      "DEPARTAMENTO": "Departamento [",
      "COBERTURA_NETA": 91.0,
      "DESERCION": 3.82,
      "REPITENCIA": 3.52
    },
    {
      "ANO": 2012,
      "DEPARTAMENTO": "Departamento \\",
      "COBERTURA_NETA": 92.1,
      "DESERCION": 5.53,
      "REPITENCIA": 2.83
    },
    {
      "ANO": 2012,
      "DEPARTAMENTO": "Departamento ]",
      "COBERTURA_NETA": 94.8,
      "DESERCION": 5.46,
      "REPITENCIA": 3.07
    },
    {
      "ANO": 2012,
      "DEPARTAMENTO": "Departamento ^",
      "COBERTURA_NETA": 95.7,
      "DESERCION": 5.7,
      "REPITENCIA": 2.24
    },
    {
      "ANO": 2012,
      "DEPARTAMENTO": "Departamento _",
      "COBERTURA_NETA": 96.5,
      "DESERCION": 5.46,
      "REPITENCIA": 2.56
    },
    {
      "ANO": 2012,
      "DEPARTAMENTO": "Departamento `",
      "COBERTURA_NETA": 98.6,
      "DESERCION": 4.94,
      "REPITENCIA": 2.9
    },
    {
      "ANO": 2012,
      "DEPARTAMENTO": "Departamento a",
      "COBERTURA_NETA": 99.7,
      "DESERCION": 5.59,
      "REPITENCIA": 2.6
    },
    {
      "ANO": 2013,
      "DEPARTAMENTO": "Departamento A",
      "COBERTURA_NETA": 55.6,
      "DESERCION": 3.95,
      "REPITENCIA": 2.38
    },
    {
      "ANO": 2013,
      "DEPARTAMENTO": "Departamento B",
      "COBERTURA_NETA": 55.8,
      "DESERCION": 3.76,
      "REPITENCIA": 2.18
    },
    {
      "ANO": 2013,
      "DEPARTAMENTO": "Departamento C",
      "COBERTURA_NETA": 58.0,
      "DESERCION": 5.13,
      "REPITENCIA": 2.28
    },
    {
      "ANO": 2013,
      "DEPARTAMENTO": "Departamento D",
      "COBERTURA_NETA": 58.8,
      "DESERCION": 4.46,
      "REPITENCIA": 3.09
    },
    {
      "ANO": 2013,
      "DEPARTAMENTO": "Departamento E",
      "COBERTURA_NETA": 61.7,
      "DESERCION": 4.56,
      "REPITENCIA": 2.42
    },
    {
      "ANO": 2013,
      "DEPARTAMENTO": "Departamento F",
      "COBERTURA_NETA": 61.4,
      "DESERCION": 3.77,
      "REPITENCIA": 2.34
    },
    {
      "ANO": 2013,
      "DEPARTAMENTO": "Departamento G",
      "COBERTURA_NETA": 62.9,
      "DESERCION": 3.33,
      "REPITENCIA": 2.8
    },
    {
      "ANO": 2013,
      "DEPARTAMENTO": "Departamento H",
      "COBERTURA_NETA": 64.5,
      "DESERCION": 5.64,
      "REPITENCIA": 2.83
    },
    {
      "ANO": 2013,
      "DEPARTAMENTO": "Departamento I",
      "COBERTURA_NETA": 66.8,
      "DESERCION": 3.6,
      "REPITENCIA": 3.3
    },
    {
      "ANO": 2013,
      "DEPARTAMENTO": "Departamento J",
      "COBERTURA_NETA": 67.7,
      "DESERCION": 5.39,
      "REPITENCIA": 2.86
    },
    {
      "ANO": 2013,
      "DEPARTAMENTO": "Departamento K",
      "COBERTURA_NETA": 69.1,
      "DESERCION": 4.36,
      "REPITENCIA": 2.28
    },
    {
      "ANO": 2013,
      "DEPARTAMENTO": "Departamento L",
      "COBERTURA_NETA": 69.7,
      "DESERCION": 5.56,
      "REPITENCIA": 2.72
    },
    {
      "ANO": 2013,
      "DEPARTAMENTO": "Departamento M",
      "COBERTURA_NETA": 72.6,
      "DESERCION": 4.26,
      "REPITENCIA": 2.11
    },
    {
      "ANO": 2013,
      "DEPARTAMENTO": "Departamento N",
      "COBERTURA_NETA": 73.6,
      "DESERCION": 3.43,
      "REPITENCIA": 2.22
    },
    {
      "ANO": 2013,
      "DEPARTAMENTO": "Departamento O",
      "COBERTURA_NETA": 74.9,
      "DESERCION": 4.03,
      "REPITENCIA": 3.49
    },
    {
      "ANO": 2013,
      "DEPARTAMENTO": "Departamento P",
      "COBERTURA_NETA": 75.4,
      "DESERCION": 5.13,
      "REPITENCIA": 2.91
    },
    {
      "ANO": 2013,
      "DEPARTAMENTO": "Departamento Q",
      "COBERTURA_NETA": 78.1,
      "DESERCION": 3.84,
      "REPITENCIA": 2.78
    },
    {
      "ANO": 2013,
      "DEPARTAMENTO": "Departamento R",
      "COBERTURA_NETA": 78.9,
      "DESERCION": 4.36,
      "REPITENCIA": 3.29
    },
    {
      "ANO": 2013,
      "DEPARTAMENTO": "Departamento S",
      "COBERTURA_NETA": 81.3,
      "DESERCION": 4.03,
      "REPITENCIA": 2.93
    },
    {
      "ANO": 2013,
      "DEPARTAMENTO": "Departamento T",
      "COBERTURA_NETA": 82.0,
      "DESERCION": 5.08,
      "REPITENCIA": 3.42
    },
    {
      "ANO": 2013,
      "DEPARTAMENTO": "Departamento U",
      "COBERTURA_NETA": 82.6,
      "DESERCION": 3.81,
      "REPITENCIA": 2.99
    },
    {
      "ANO": 2013,
      "DEPARTAMENTO": "Departamento V",
      "COBERTURA_NETA": 83.9,
      "DESERCION": 3.72,
      "REPITENCIA": 2.11
    },
    {
      "ANO": 2013,
      "DEPARTAMENTO": "Departamento W",
      "COBERTURA_NETA": 85.0,
      "DESERCION": 4.38,
      "REPITENCIA": 2.89
    },
    {
      "ANO": 2013,
      "DEPARTAMENTO": "Departamento X",
      "COBERTURA_NETA": 86.9,
      "DESERCION": 3.86,
      "REPITENCIA": 3.06
    },
    {
      "ANO": 2013,
      "DEPARTAMENTO": "Departamento Y",
      "COBERTURA_NETA": 89.2,
      "DESERCION": 4.39,
      "REPITENCIA": 3.03
    },
    {
      "ANO": 2013,
      "DEPARTAMENTO": "Departamento Z",
      "COBERTURA_NETA": 91.0,
      "DESERCION": 5.19,
      "REPITENCIA": 2.94
    },
    {
      "ANO": 2013,
      "DEPARTAMENTO": "Departamento [",
      "COBERTURA_NETA": 91.9,
      "DESERCION": 5.54,
      "REPITENCIA": 2.64
    },
    {
      "ANO": 2013,
      "DEPARTAMENTO": "Departamento \\",
      "COBERTURA_NETA": 93.0,
      "DESERCION": 4.85,
      "REPITENCIA": 3.36
    },
    {
      "ANO": 2013,
      "DEPARTAMENTO": "Departamento ]",
      "COBERTURA_NETA": 95.0,
      "DESERCION": 3.47,
      "REPITENCIA": 2.25
    },
    {
      "ANO": 2013,
      "DEPARTAMENTO": "Departamento ^",
      "COBERTURA_NETA": 95.4,
      "DESERCION": 5.1,
      "REPITENCIA": 2.85
    },
    {
      "ANO": 2013,
      "DEPARTAMENTO": "Departamento _",
      "COBERTURA_NETA": 96.7,
      "DESERCION": 3.6,
      "REPITENCIA": 3.03
    },
    {
      "ANO": 2013,
      "DEPARTAMENTO": "Departamento `",
      "COBERTURA_NETA": 99.0,
      "DESERCION": 5.56,
      "REPITENCIA": 2.75
    },
    {
      "ANO": 2013,
      "DEPARTAMENTO": "Departamento a",
      "COBERTURA_NETA": 99.9,
      "DESERCION": 3.49,
      "REPITENCIA": 2.06
    },
    {
      "ANO": 2014,
      "DEPARTAMENTO": "Departamento A",
      "COBERTURA_NETA": 55.1,
      "DESERCION": 3.77,
      "REPITENCIA": 2.28
    },
    {
      "ANO": 2014,
      "DEPARTAMENTO": "Departamento B",
      "COBERTURA_NETA": 55.8,
      "DESERCION": 5.31,
      "REPITENCIA": 3.15
    },
    {
      "ANO": 2014,
      "DEPARTAMENTO": "Departamento C",
      "COBERTURA_NETA": 58.2,
      "DESERCION": 5.28,
      "REPITENCIA": 3.4
    },
    {
      "ANO": 2014,
      "DEPARTAMENTO": "Departamento D",
      "COBERTURA_NETA": 59.8,
      "DESERCION": 3.65,
      "REPITENCIA": 1.96
    },
    {
      "ANO": 2014,
      "DEPARTAMENTO": "Departamento E",
      "COBERTURA_NETA": 61.4,
      "DESERCION": 4.13,
      "REPITENCIA": 2.88
    },
    {
      "ANO": 2014,
      "DEPARTAMENTO": "Departamento F",
      "COBERTURA_NETA": 63.1,
      "DESERCION": 3.44,
      "REPITENCIA": 2.78
    },
    {
      "ANO": 2014,
      "DEPARTAMENTO": "Departamento G",
      "COBERTURA_NETA": 63.9,
      "DESERCION": 4.18,
      "REPITENCIA": 2.04
    },
    {
      "ANO": 2014,
      "DEPARTAMENTO": "Departamento H",
      "COBERTURA_NETA": 64.7,
      "DESERCION": 3.8,
      "REPITENCIA": 2.91
    },
    {
      "ANO": 2014,
      "DEPARTAMENTO": "Departamento I",
      "COBERTURA_NETA": 67.2,
      "DESERCION": 3.79,
      "REPITENCIA": 2.94
    },
    {
      "ANO": 2014,
      "DEPARTAMENTO": "Departamento J",
      "COBERTURA_NETA": 67.4,
      "DESERCION": 5.27,
      "REPITENCIA": 3.12
    },
    {
      "ANO": 2014,
      "DEPARTAMENTO": "Departamento K",
      "COBERTURA_NETA": 69.3,
      "DESERCION": 4.09,
      "REPITENCIA": 2.37
    },
    {
      "ANO": 2014,
      "DEPARTAMENTO": "Departamento L",
      "COBERTURA_NETA": 70.3,
      "DESERCION": 5.33,
      "REPITENCIA": 2.51
    },
    {
      "ANO": 2014,
      "DEPARTAMENTO": "Departamento M",
      "COBERTURA_NETA": 72.1,
      "DESERCION": 5.37,
      "REPITENCIA": 2.89
    },
    {
      "ANO": 2014,
      "DEPARTAMENTO": "Departamento N",
      "COBERTURA_NETA": 73.5,
      "DESERCION": 3.99,
      "REPITENCIA": 2.18
    },
    {
      "ANO": 2014,
      "DEPARTAMENTO": "Departamento O",
      "COBERTURA_NETA": 74.6,
      "DESERCION": 4.82,
      "REPITENCIA": 2.84
    },
    {
      "ANO": 2014,
      "DEPARTAMENTO": "Departamento P",
      "COBERTURA_NETA": 76.8,
      "DESERCION": 3.49,
      "REPITENCIA": 2.72
    },
    {
      "ANO": 2014,
      "DEPARTAMENTO": "Departamento Q",
      "COBERTURA_NETA": 78.5,
      "DESERCION": 4.05,
      "REPITENCIA": 2.95
    },
    {
      "ANO": 2014,
      "DEPARTAMENTO": "Departamento R",
      "COBERTURA_NETA": 78.3,
      "DESERCION": 5.34,
      "REPITENCIA": 2.81
    },
    {
      "ANO": 2014,
      "DEPARTAMENTO": "Departamento S",
      "COBERTURA_NETA": 79.9,
      "DESERCION": 3.38,
      "REPITENCIA": 2.73
    },
    {
      "ANO": 2014,
      "DEPARTAMENTO": "Departamento T",
      "COBERTURA_NETA": 81.9,
      "DESERCION": 3.22,
      "REPITENCIA": 3.39
    },
    {
      "ANO": 2014,
      "DEPARTAMENTO": "Departamento U",
      "COBERTURA_NETA": 84.1,
      "DESERCION": 4.11,
      "REPITENCIA": 2.08
    },
    {
      "ANO": 2014,
      "DEPARTAMENTO": "Departamento V",
      "COBERTURA_NETA": 85.3,
      "DESERCION": 4.2,
      "REPITENCIA": 2.97
    },
    {
      "ANO": 2014,
      "DEPARTAMENTO": "Departamento W",
      "COBERTURA_NETA": 86.1,
      "DESERCION": 3.66,
      "REPITENCIA": 3.15
    },
    {
      "ANO": 2014,
      "DEPARTAMENTO": "Departamento X",
      "COBERTURA_NETA": 88.4,
      "DESERCION": 3.58,
      "REPITENCIA": 2.73
    },
    {
      "ANO": 2014,
      "DEPARTAMENTO": "Departamento Y",
      "COBERTURA_NETA": 88.6,
      "DESERCION": 5.21,
      "REPITENCIA": 2.66
    },
    {
      "ANO": 2014,
      "DEPARTAMENTO": "Departamento Z",
      "COBERTURA_NETA": 91.0,
      "DESERCION": 5.07,
      "REPITENCIA": 2.31
    },
    {
      "ANO": 2014,
      "DEPARTAMENTO": "Departamento [",
      "COBERTURA_NETA": 92.2,
      "DESERCION": 4.0,
      "REPITENCIA": 3.3
    },
    {
      "ANO": 2014,
      "DEPARTAMENTO": "Departamento \\",
      "COBERTURA_NETA": 93.1,
      "DESERCION": 4.97,
      "REPITENCIA": 2.32
    },
    {
      "ANO": 2014,
      "DEPARTAMENTO": "Departamento ]",
      "COBERTURA_NETA": 94.0,
      "DESERCION": 4.41,
      "REPITENCIA": 3.4
    },
    {
      "ANO": 2014,
      "DEPARTAMENTO": "Departamento ^",
      "COBERTURA_NETA": 95.8,
      "DESERCION": 3.36,
      "REPITENCIA": 2.71
    },
    {
      "ANO": 2014,
      "DEPARTAMENTO": "Departamento _",
      "COBERTURA_NETA": 96.9,
      "DESERCION": 4.32,
      "REPITENCIA": 2.72
    },
    {
      "ANO": 2014,
      "DEPARTAMENTO": "Departamento `",
      "COBERTURA_NETA": 98.6,
      "DESERCION": 3.77,
      "REPITENCIA": 2.18
    },
    {
      "ANO": 2014,
      "DEPARTAMENTO": "Departamento a",
      "COBERTURA_NETA": 100.4,
      "DESERCION": 4.37,
      "REPITENCIA": 2.25
    },
    {
      "ANO": 2015,
      "DEPARTAMENTO": "Departamento A",
      "COBERTURA_NETA": 55.9,
      "DESERCION": 2.9,
      "REPITENCIA": 2.82
    },
    {
      "ANO": 2015,
      "DEPARTAMENTO": "Departamento B",
      "COBERTURA_NETA": 57.1,
      "DESERCION": 4.75,
      "REPITENCIA": 2.28
    },
    {
      "ANO": 2015,
      "DEPARTAMENTO": "Departamento C",
      "COBERTURA_NETA": 58.4,
      "DESERCION": 4.77,
      "REPITENCIA": 3.17
    },
    {
      "ANO": 2015,
      "DEPARTAMENTO": "Departamento D",
      "COBERTURA_NETA": 59.5,
      "DESERCION": 2.89,
      "REPITENCIA": 2.45
    },
    {
      "ANO": 2015,
      "DEPARTAMENTO": "Departamento E",
      "COBERTURA_NETA": 61.1,
      "DESERCION": 4.89,
      "REPITENCIA": 3.01
    },
    {
      "ANO": 2015,
      "DEPARTAMENTO": "Departamento F",
      "COBERTURA_NETA": 62.2,
      "DESERCION": 4.06,
      "REPITENCIA": 2.39
    },
    {
      "ANO": 2015,
      "DEPARTAMENTO": "Departamento G",
      "COBERTURA_NETA": 64.2,
      "DESERCION": 3.78,
      "REPITENCIA": 2.68
    },
    {
      "ANO": 2015,
      "DEPARTAMENTO": "Departamento H",
      "COBERTURA_NETA": 64.4,
      "DESERCION": 3.93,
      "REPITENCIA": 3.15
    },
    {
      "ANO": 2015,
      "DEPARTAMENTO": "Departamento I",
      "COBERTURA_NETA": 66.2,
      "DESERCION": 4.46,
      "REPITENCIA": 2.67
    },
    {
      "ANO": 2015,
      "DEPARTAMENTO": "Departamento J",
      "COBERTURA_NETA": 68.6,
      "DESERCION": 4.85,
      "REPITENCIA": 2.99
    },
    {
      "ANO": 2015,
      "DEPARTAMENTO": "Departamento K",
      "COBERTURA_NETA": 69.1,
      "DESERCION": 3.56,
      "REPITENCIA": 2.78
    },
    {
      "ANO": 2015,
      "DEPARTAMENTO": "Departamento L",
      "COBERTURA_NETA": 71.2,
      "DESERCION": 4.89,
      "REPITENCIA": 1.75
    },
    {
      "ANO": 2015,
      "DEPARTAMENTO": "Departamento M",
      "COBERTURA_NETA": 71.3,
      "DESERCION": 4.31,
      "REPITENCIA": 3.08
    },
    {
      "ANO": 2015,
      "DEPARTAMENTO": "Departamento N",
      "COBERTURA_NETA": 74.5,
      "DESERCION": 4.59,
      "REPITENCIA": 2.35
    },
    {
      "ANO": 2015,
      "DEPARTAMENTO": "Departamento O",
      "COBERTURA_NETA": 74.1,
      "DESERCION": 4.32,
      "REPITENCIA": 3.01
    },
    {
      "ANO": 2015,
      "DEPARTAMENTO": "Departamento P",
      "COBERTURA_NETA": 76.2,
      "DESERCION": 4.47,
      "REPITENCIA": 3.06
    },
    {
      "ANO": 2015,
      "DEPARTAMENTO": "Departamento Q",
      "COBERTURA_NETA": 76.8,
      "DESERCION": 4.71,
      "REPITENCIA": 2.14
    },
    {
      "ANO": 2015,
      "DEPARTAMENTO": "Departamento R",
      "COBERTURA_NETA": 78.9,
      "DESERCION": 3.15,
      "REPITENCIA": 2.5
    },
    {
      "ANO": 2015,
      "DEPARTAMENTO": "Departamento S",
      "COBERTURA_NETA": 80.7,
      "DESERCION": 4.7,
      "REPITENCIA": 1.95
    },
    {
      "ANO": 2015,
      "DEPARTAMENTO": "Departamento T",
      "COBERTURA_NETA": 81.1,
      "DESERCION": 4.89,
      "REPITENCIA": 2.63
    },
    {
      "ANO": 2015,
      "DEPARTAMENTO": "Departamento U",
      "COBERTURA_NETA": 82.8,
      "DESERCION": 4.99,
      "REPITENCIA": 1.91
    },
    {
      "ANO": 2015,
      "DEPARTAMENTO": "Departamento V",
      "COBERTURA_NETA": 84.6,
      "DESERCION": 3.41,
      "REPITENCIA": 2.08
    },
    {
      "ANO": 2015,
      "DEPARTAMENTO": "Departamento W",
      "COBERTURA_NETA": 85.1,
      "DESERCION": 4.73,
      "REPITENCIA": 3.05
    },
    {
      "ANO": 2015,
      "DEPARTAMENTO": "Departamento X",
      "COBERTURA_NETA": 87.9,
      "DESERCION": 3.18,
      "REPITENCIA": 2.36
    },
    {
      "ANO": 2015,
      "DEPARTAMENTO": "Departamento Y",
      "COBERTURA_NETA": 88.6,
      "DESERCION": 4.21,
      "REPITENCIA": 2.66
    },
    {
      "ANO": 2015,
      "DEPARTAMENTO": "Departamento Z",
      "COBERTURA_NETA": 90.2,
      "DESERCION": 3.4,
      "REPITENCIA": 2.97
    },
    {
      "ANO": 2015,
      "DEPARTAMENTO": "Departamento [",
      "COBERTURA_NETA": 91.1,
      "DESERCION": 3.72,
      "REPITENCIA": 2.42
    },
    {
      "ANO": 2015,
      "DEPARTAMENTO": "Departamento \\",
      "COBERTURA_NETA": 92.6,
      "DESERCION": 4.17,
      "REPITENCIA": 2.56
    },
    {
      "ANO": 2015,
      "DEPARTAMENTO": "Departamento ]",
      "COBERTURA_NETA": 95.5,
      "DESERCION": 3.51,
      "REPITENCIA": 3.17
    },
    {
      "ANO": 2015,
      "DEPARTAMENTO": "Departamento ^",
      "COBERTURA_NETA": 96.2,
      "DESERCION": 3.46,
      "REPITENCIA": 2.55
    },
    {
      "ANO": 2015,
      "DEPARTAMENTO": "Departamento _",
      "COBERTURA_NETA": 97.7,
      "DESERCION": 4.59,
      "REPITENCIA": 1.77
    },
    {
      "ANO": 2015,
      "DEPARTAMENTO": "Departamento `",
      "COBERTURA_NETA": 98.9,
      "DESERCION": 3.99,
      "REPITENCIA": 3.06
    },
    {
      "ANO": 2015,
      "DEPARTAMENTO": "Departamento a",
      "COBERTURA_NETA": 99.7,
      "DESERCION": 4.72,
      "REPITENCIA": 2.61
    },
    {
      "ANO": 2016,
      "DEPARTAMENTO": "Departamento A",
      "COBERTURA_NETA": 55.1,
      "DESERCION": 4.63,
      "REPITENCIA": 2.93
    },
    {
      "ANO": 2016,
      "DEPARTAMENTO": "Departamento B",
      "COBERTURA_NETA": 57.2,
      "DESERCION": 4.83,
      "REPITENCIA": 2.99
    },
    {
      "ANO": 2016,
      "DEPARTAMENTO": "Departamento C",
      "COBERTURA_NETA": 58.9,
      "DESERCION": 4.61,
      "REPITENCIA": 3.36
    },
    {
      "ANO": 2016,
      "DEPARTAMENTO": "Departamento D",
      "COBERTURA_NETA": 59.9,
      "DESERCION": 3.84,
      "REPITENCIA": 2.66
    },
    {
      "ANO": 2016,
      "DEPARTAMENTO": "Departamento E",
      "COBERTURA_NETA": 61.2,
      "DESERCION": 4.86,
      "REPITENCIA": 2.14
    },
    {
      "ANO": 2016,
      "DEPARTAMENTO": "Departamento F",
      "COBERTURA_NETA": 62.0,
      "DESERCION": 4.89,
      "REPITENCIA": 2.26
    },
    {
      "ANO": 2016,
      "DEPARTAMENTO": "Departamento G",
      "COBERTURA_NETA": 63.1,
      "DESERCION": 4.39,
      "REPITENCIA": 3.46
    },
    {
      "ANO": 2016,
      "DEPARTAMENTO": "Departamento H",
      "COBERTURA_NETA": 65.3,
      "DESERCION": 5.29,
      "REPITENCIA": 3.25
    },
    {
      "ANO": 2016,
      "DEPARTAMENTO": "Departamento I",
      "COBERTURA_NETA": 66.1,
      "DESERCION": 5.08,
      "REPITENCIA": 2.72
    },
    {
      "ANO": 2016,
      "DEPARTAMENTO": "Departamento J",
      "COBERTURA_NETA": 68.6,
      "DESERCION": 4.89,
      "REPITENCIA": 2.51
    },
    {
      "ANO": 2016,
      "DEPARTAMENTO": "Departamento K",
      "COBERTURA_NETA": 68.6,
      "DESERCION": 5.41,
      "REPITENCIA": 2.21
    },
    {
      "ANO": 2016,
      "DEPARTAMENTO": "Departamento L",
      "COBERTURA_NETA": 71.7,
      "DESERCION": 5.16,
      "REPITENCIA": 3.09
    },
    {
      "ANO": 2016,
      "DEPARTAMENTO": "Departamento M",
      "COBERTURA_NETA": 73.2,
      "DESERCION": 5.42,
      "REPITENCIA": 3.21
    },
    {
      "ANO": 2016,
      "DEPARTAMENTO": "Departamento N",
      "COBERTURA_NETA": 73.3,
      "DESERCION": 5.0,
      "REPITENCIA": 2.02
    },
    {
      "ANO": 2016,
      "DEPARTAMENTO": "Departamento O",
      "COBERTURA_NETA": 75.1,
      "DESERCION": 4.19,
      "REPITENCIA": 3.01
    },
    {
      "ANO": 2016,
      "DEPARTAMENTO": "Departamento P",
      "COBERTURA_NETA": 76.7,
      "DESERCION": 4.5,
      "REPITENCIA": 3.23
    },
    {
      "ANO": 2016,
      "DEPARTAMENTO": "Departamento Q",
      "COBERTURA_NETA": 78.7,
      "DESERCION": 3.36,
      "REPITENCIA": 2.35
    },
    {
      "ANO": 2016,
      "DEPARTAMENTO": "Departamento R",
      "COBERTURA_NETA": 78.3,
      "DESERCION": 5.22,
      "REPITENCIA": 2.84
    },
    {
      "ANO": 2016,
      "DEPARTAMENTO": "Departamento S",
      "COBERTURA_NETA": 81.4,
      "DESERCION": 3.63,
      "REPITENCIA": 2.09
    },
    {
      "ANO": 2016,
      "DEPARTAMENTO": "Departamento T",
      "COBERTURA_NETA": 82.6,
      "DESERCION": 5.28,
      "REPITENCIA": 2.45
    },
    {
      "ANO": 2016,
      "DEPARTAMENTO": "Departamento U",
      "COBERTURA_NETA": 83.2,
      "DESERCION": 3.44,
      "REPITENCIA": 3.42
    },
    {
      "ANO": 2016,
      "DEPARTAMENTO": "Departamento V",
      "COBERTURA_NETA": 84.4,
      "DESERCION": 4.28,
      "REPITENCIA": 2.15
    },
    {
      "ANO": 2016,
      "DEPARTAMENTO": "Departamento W",
      "COBERTURA_NETA": 87.0,
      "DESERCION": 3.43,
      "REPITENCIA": 2.68
    },
    {
      "ANO": 2016,
      "DEPARTAMENTO": "Departamento X",
      "COBERTURA_NETA": 87.9,
      "DESERCION": 4.88,
      "REPITENCIA": 3.42
    },
    {
      "ANO": 2016,
      "DEPARTAMENTO": "Departamento Y",
      "COBERTURA_NETA": 88.8,
      "DESERCION": 4.88,
      "REPITENCIA": 2.23
    },
    {
      "ANO": 2016,
      "DEPARTAMENTO": "Departamento Z",
      "COBERTURA_NETA": 90.2,
      "DESERCION": 3.34,
      "REPITENCIA": 2.73
    },
    {
      "ANO": 2016,
      "DEPARTAMENTO": "Departamento [",
      "COBERTURA_NETA": 91.6,
      "DESERCION": 5.38,
      "REPITENCIA": 2.05
    },
    {
      "ANO": 2016,
      "DEPARTAMENTO": "Departamento \\",
      "COBERTURA_NETA": 92.9,
      "DESERCION": 4.16,
      "REPITENCIA": 3.43
    },
    {
      "ANO": 2016,
      "DEPARTAMENTO": "Departamento ]",
      "COBERTURA_NETA": 95.3,
      "DESERCION": 3.34,
      "REPITENCIA": 3.03
    },
    {
      "ANO": 2016,
      "DEPARTAMENTO": "Departamento ^",
      "COBERTURA_NETA": 96.1,
      "DESERCION": 5.45,
      "REPITENCIA": 2.54
    },
    {
      "ANO": 2016,
      "DEPARTAMENTO": "Departamento _",
      "COBERTURA_NETA": 97.2,
      "DESERCION": 3.56,
      "REPITENCIA": 2.18
    },
    {
      "ANO": 2016,
      "DEPARTAMENTO": "Departamento `",
      "COBERTURA_NETA": 99.5,
      "DESERCION": 4.19,
      "REPITENCIA": 2.99
    },
    {
      "ANO": 2016,
      "DEPARTAMENTO": "Departamento a",
      "COBERTURA_NETA": 100.5,
      "DESERCION": 4.53,
      "REPITENCIA": 2.03
    },
    {
      "ANO": 2017,
      "DEPARTAMENTO": "Departamento A",
      "COBERTURA_NETA": 56.1,
      "DESERCION": 3.38,
      "REPITENCIA": 2.59
    },
    {
      "ANO": 2017,
      "DEPARTAMENTO": "Departamento B",
      "COBERTURA_NETA": 57.0,
      "DESERCION": 2.96,
      "REPITENCIA": 3.55
    },
    {
      "ANO": 2017,
      "DEPARTAMENTO": "Departamento C",
      "COBERTURA_NETA": 57.7,
      "DESERCION": 3.32,
      "REPITENCIA": 3.7
    },
    {
      "ANO": 2017,
      "DEPARTAMENTO": "Departamento D",
      "COBERTURA_NETA": 59.3,
      "DESERCION": 3.15,
      "REPITENCIA": 3.75
    },
    {
      "ANO": 2017,
      "DEPARTAMENTO": "Departamento E",
      "COBERTURA_NETA": 60.1,
      "DESERCION": 4.86,
      "REPITENCIA": 2.62
    },
    {
      "ANO": 2017,
      "DEPARTAMENTO": "Departamento F",
      "COBERTURA_NETA": 61.7,
      "DESERCION": 3.4,
      "REPITENCIA": 2.66
    },
    {
      "ANO": 2017,
      "DEPARTAMENTO": "Departamento G",
      "COBERTURA_NETA": 64.2,
      "DESERCION": 2.86,
      "REPITENCIA": 2.42
    },
    {
      "ANO": 2017,
      "DEPARTAMENTO": "Departamento H",
      "COBERTURA_NETA": 65.9,
      "DESERCION": 3.37,
      "REPITENCIA": 2.89
    },
    {
      "ANO": 2017,
      "DEPARTAMENTO": "Departamento I",
      "COBERTURA_NETA": 66.0,
      "DESERCION": 2.93,
      "REPITENCIA": 3.51
    },
    {
      "ANO": 2017,
      "DEPARTAMENTO": "Departamento J",
      "COBERTURA_NETA": 68.1,
      "DESERCION": 4.59,
      "REPITENCIA": 3.11
    },
    {
      "ANO": 2017,
      "DEPARTAMENTO": "Departamento K",
      "COBERTURA_NETA": 70.0,
      "DESERCION": 4.03,
      "REPITENCIA": 2.56
    },
    {
      "ANO": 2017,
      "DEPARTAMENTO": "Departamento L",
      "COBERTURA_NETA": 70.9,
      "DESERCION": 5.07,
      "REPITENCIA": 2.47
    },
    {
      "ANO": 2017,
      "DEPARTAMENTO": "Departamento M",
      "COBERTURA_NETA": 72.8,
      "DESERCION": 4.88,
      "REPITENCIA": 3.18
    },
    {
      "ANO": 2017,
      "DEPARTAMENTO": "Departamento N",
      "COBERTURA_NETA": 73.6,
      "DESERCION": 5.11,
      "REPITENCIA": 2.49
    },
    {
      "ANO": 2017,
      "DEPARTAMENTO": "Departamento O",
      "COBERTURA_NETA": 75.0,
      "DESERCION": 3.76,
      "REPITENCIA": 3.43
    },
    {
      "ANO": 2017,
      "DEPARTAMENTO": "Departamento P",
      "COBERTURA_NETA": 76.5,
      "DESERCION": 4.98,
      "REPITENCIA": 2.51
    },
    {
      "ANO": 2017,
      "DEPARTAMENTO": "Departamento Q",
      "COBERTURA_NETA": 77.0,
      "DESERCION": 4.26,
      "REPITENCIA": 2.5
    },
    {
      "ANO": 2017,
      "DEPARTAMENTO": "Departamento R",
      "COBERTURA_NETA": 78.8,
      "DESERCION": 4.32,
      "REPITENCIA": 3.22
    },
    {
      "ANO": 2017,
      "DEPARTAMENTO": "Departamento S",
      "COBERTURA_NETA": 80.3,
      "DESERCION": 5.19,
      "REPITENCIA": 3.2
    },
    {
      "ANO": 2017,
      "DEPARTAMENTO": "Departamento T",
      "COBERTURA_NETA": 82.0,
      "DESERCION": 4.25,
      "REPITENCIA": 2.55
    },
    {
      "ANO": 2017,
      "DEPARTAMENTO": "Departamento U",
      "COBERTURA_NETA": 83.9,
      "DESERCION": 4.85,
      "REPITENCIA": 3.38
    },
    {
      "ANO": 2017,
      "DEPARTAMENTO": "Departamento V",
      "COBERTURA_NETA": 85.4,
      "DESERCION": 4.53,
      "REPITENCIA": 2.72
    },
    {
      "ANO": 2017,
      "DEPARTAMENTO": "Departamento W",
      "COBERTURA_NETA": 86.2,
      "DESERCION": 3.35,
      "REPITENCIA": 2.91
    },
    {
      "ANO": 2017,
      "DEPARTAMENTO": "Departamento X",
      "COBERTURA_NETA": 87.6,
      "DESERCION": 3.8,
      "REPITENCIA": 2.54
    },
    {
      "ANO": 2017,
      "DEPARTAMENTO": "Departamento Y",
      "COBERTURA_NETA": 88.9,
      "DESERCION": 4.4,
      "REPITENCIA": 2.96
    },
    {
      "ANO": 2017,
      "DEPARTAMENTO": "Departamento Z",
      "COBERTURA_NETA": 89.8,
      "DESERCION": 5.02,
      "REPITENCIA": 2.5
    },
    {
      "ANO": 2017,
      "DEPARTAMENTO": "Departamento [",
      "COBERTURA_NETA": 92.5,
      "DESERCION": 3.02,
      "REPITENCIA": 2.54
    },
    {
      "ANO": 2017,
      "DEPARTAMENTO": "Departamento \\",
      "COBERTURA_NETA": 93.8,
      "DESERCION": 4.75,
      "REPITENCIA": 3.23
    },
    {
      "ANO": 2017,
      "DEPARTAMENTO": "Departamento ]",
      "COBERTURA_NETA": 94.9,
      "DESERCION": 4.15,
      "REPITENCIA": 2.89
    },
    {
      "ANO": 2017,
      "DEPARTAMENTO": "Departamento ^",
      "COBERTURA_NETA": 95.3,
      "DESERCION": 3.65,
      "REPITENCIA": 3.4
    },
    {
      "ANO": 2017,
      "DEPARTAMENTO": "Departamento _",
      "COBERTURA_NETA": 98.0,
      "DESERCION": 4.88,
      "REPITENCIA": 3.48
    },
    {
      "ANO": 2017,
      "DEPARTAMENTO": "Departamento `",
      "COBERTURA_NETA": 99.8,
      "DESERCION": 4.24,
      "REPITENCIA": 2.93
    },
    {
      "ANO": 2017,
      "DEPARTAMENTO": "Departamento a",
      "COBERTURA_NETA": 100.4,
      "DESERCION": 3.31,
      "REPITENCIA": 3.39
    },
    {
      "ANO": 2018,
      "DEPARTAMENTO": "Departamento A",
      "COBERTURA_NETA": 55.0,
      "DESERCION": 2.56,
      "REPITENCIA": 3.17
    },
    {
      "ANO": 2018,
      "DEPARTAMENTO": "Departamento B",
      "COBERTURA_NETA": 56.7,
      "DESERCION": 4.13,
      "REPITENCIA": 2.76
    },
    {
      "ANO": 2018,
      "DEPARTAMENTO": "Departamento C",
      "COBERTURA_NETA": 59.0,
      "DESERCION": 4.33,
      "REPITENCIA": 3.36
    },
    {
      "ANO": 2018,
      "DEPARTAMENTO": "Departamento D",
      "COBERTURA_NETA": 60.4,
      "DESERCION": 3.77,
      "REPITENCIA": 2.86
    },
    {
      "ANO": 2018,
      "DEPARTAMENTO": "Departamento E",
      "COBERTURA_NETA": 60.2,
      "DESERCION": 4.53,
      "REPITENCIA": 3.14
    },
    {
      "ANO": 2018,
      "DEPARTAMENTO": "Departamento F",
      "COBERTURA_NETA": 62.1,
      "DESERCION": 2.73,
      "REPITENCIA": 2.95
    },
    {
      "ANO": 2018,
      "DEPARTAMENTO": "Departamento G",
      "COBERTURA_NETA": 63.6,
      "DESERCION": 3.12,
      "REPITENCIA": 1.91
    },
    {
      "ANO": 2018,
      "DEPARTAMENTO": "Departamento H",
      "COBERTURA_NETA": 66.1,
      "DESERCION": 3.66,
      "REPITENCIA": 2.5
    },
    {
      "ANO": 2018,
      "DEPARTAMENTO": "Departamento I",
      "COBERTURA_NETA": 66.0,
      "DESERCION": 3.82,
      "REPITENCIA": 1.95
    },
    {
      "ANO": 2018,
      "DEPARTAMENTO": "Departamento J",
      "COBERTURA_NETA": 68.7,
      "DESERCION": 2.82,
      "REPITENCIA": 2.53
    },
    {
      "ANO": 2018,
      "DEPARTAMENTO": "Departamento K",
      "COBERTURA_NETA": 69.2,
      "DESERCION": 3.19,
      "REPITENCIA": 2.98
    },
    {
      "ANO": 2018,
      "DEPARTAMENTO": "Departamento L",
      "COBERTURA_NETA": 71.5,
      "DESERCION": 3.66,
      "REPITENCIA": 2.03
    },
    {
      "ANO": 2018,
      "DEPARTAMENTO": "Departamento M",
      "COBERTURA_NETA": 71.5,
      "DESERCION": 2.68,
      "REPITENCIA": 2.83
    },
    {
      "ANO": 2018,
      "DEPARTAMENTO": "Departamento N",
      "COBERTURA_NETA": 74.1,
      "DESERCION": 2.95,
      "REPITENCIA": 2.89
    },
    {
      "ANO": 2018,
      "DEPARTAMENTO": "Departamento O",
      "COBERTURA_NETA": 75.1,
      "DESERCION": 3.36,
      "REPITENCIA": 2.31
    },
    {
      "ANO": 2018,
      "DEPARTAMENTO": "Departamento P",
      "COBERTURA_NETA": 77.1,
      "DESERCION": 2.57,
      "REPITENCIA": 2.54
    },
    {
      "ANO": 2018,
      "DEPARTAMENTO": "Departamento Q",
      "COBERTURA_NETA": 77.5,
      "DESERCION": 3.93,
      "REPITENCIA": 2.63
    },
    {
      "ANO": 2018,
      "DEPARTAMENTO": "Departamento R",
      "COBERTURA_NETA": 79.7,
      "DESERCION": 2.41,
      "REPITENCIA": 2.49
    },
    {
      "ANO": 2018,
      "DEPARTAMENTO": "Departamento S",
      "COBERTURA_NETA": 81.0,
      "DESERCION": 2.32,
      "REPITENCIA": 2.35
    },
    {
      "ANO": 2018,
      "DEPARTAMENTO": "Departamento T",
      "COBERTURA_NETA": 81.6,
      "DESERCION": 2.63,
      "REPITENCIA": 2.28
    },
    {
      "ANO": 2018,
      "DEPARTAMENTO": "Departamento U",
      "COBERTURA_NETA": 83.2,
      "DESERCION": 2.32,
      "REPITENCIA": 3.02
    },
    {
      "ANO": 2018,
      "DEPARTAMENTO": "Departamento V",
      "COBERTURA_NETA": 84.3,
      "DESERCION": 3.21,
      "REPITENCIA": 2.96
    },
    {
      "ANO": 2018,
      "DEPARTAMENTO": "Departamento W",
      "COBERTURA_NETA": 86.4,
      "DESERCION": 4.3,
      "REPITENCIA": 3.11
    },
    {
      "ANO": 2018,
      "DEPARTAMENTO": "Departamento X",
      "COBERTURA_NETA": 86.9,
      "DESERCION": 4.37,
      "REPITENCIA": 1.96
    },
    {
      "ANO": 2018,
      "DEPARTAMENTO": "Departamento Y",
      "COBERTURA_NETA": 88.2,
      "DESERCION": 4.51,
      "REPITENCIA": 3.19
    },
    {
      "ANO": 2018,
      "DEPARTAMENTO": "Departamento Z",
      "COBERTURA_NETA": 90.7,
      "DESERCION": 3.68,
      "REPITENCIA": 2.96
    },
    {
      "ANO": 2018,
      "DEPARTAMENTO": "Departamento [",
      "COBERTURA_NETA": 91.8,
      "DESERCION": 2.58,
      "REPITENCIA": 1.93
    },
    {
      "ANO": 2018,
      "DEPARTAMENTO": "Departamento \\",
      "COBERTURA_NETA": 93.0,
      "DESERCION": 4.22,
      "REPITENCIA": 2.83
    },
    {
      "ANO": 2018,
      "DEPARTAMENTO": "Departamento ]",
      "COBERTURA_NETA": 95.4,
      "DESERCION": 4.51,
      "REPITENCIA": 2.03
    },
    {
      "ANO": 2018,
      "DEPARTAMENTO": "Departamento ^",
      "COBERTURA_NETA": 96.8,
      "DESERCION": 2.88,
      "REPITENCIA": 2.78
    },
    {
      "ANO": 2018,
      "DEPARTAMENTO": "Departamento _",
      "COBERTURA_NETA": 97.6,
      "DESERCION": 3.25,
      "REPITENCIA": 2.37
    },
    {
      "ANO": 2018,
      "DEPARTAMENTO": "Departamento `",
      "COBERTURA_NETA": 98.6,
      "DESERCION": 3.1,
      "REPITENCIA": 2.15
    },
    {
      "ANO": 2018,
      "DEPARTAMENTO": "Departamento a",
      "COBERTURA_NETA": 100.4,
      "DESERCION": 2.57,
      "REPITENCIA": 2.66
    },
    {
      "ANO": 2019,
      "DEPARTAMENTO": "Departamento A",
      "COBERTURA_NETA": 56.5,
      "DESERCION": 3.14,
      "REPITENCIA": 3.19
    },
    {
      "ANO": 2019,
      "DEPARTAMENTO": "Departamento B",
      "COBERTURA_NETA": 57.7,
      "DESERCION": 4.26,
      "REPITENCIA": 2.45
    },
    {
      "ANO": 2019,
      "DEPARTAMENTO": "Departamento C",
      "COBERTURA_NETA": 57.7,
      "DESERCION": 2.77,
      "REPITENCIA": 3.0
    },
    {
      "ANO": 2019,
      "DEPARTAMENTO": "Departamento D",
      "COBERTURA_NETA": 60.4,
      "DESERCION": 3.87,
      "REPITENCIA": 2.37
    },
    {
      "ANO": 2019,
      "DEPARTAMENTO": "Departamento E",
      "COBERTURA_NETA": 61.8,
      "DESERCION": 3.49,
      "REPITENCIA": 3.23
    },
    {
      "ANO": 2019,
      "DEPARTAMENTO": "Departamento F",
      "COBERTURA_NETA": 63.2,
      "DESERCION": 3.38,
      "REPITENCIA": 3.49
    },
    {
      "ANO": 2019,
      "DEPARTAMENTO": "Departamento G",
      "COBERTURA_NETA": 64.2,
      "DESERCION": 3.82,
      "REPITENCIA": 3.04
    },
    {
      "ANO": 2019,
      "DEPARTAMENTO": "Departamento H",
      "COBERTURA_NETA": 66.2,
      "DESERCION": 3.81,
      "REPITENCIA": 2.33
    },
    {
      "ANO": 2019,
      "DEPARTAMENTO": "Departamento I",
      "COBERTURA_NETA": 66.0,
      "DESERCION": 3.36,
      "REPITENCIA": 2.55
    },
    {
      "ANO": 2019,
      "DEPARTAMENTO": "Departamento J",
      "COBERTURA_NETA": 67.8,
      "DESERCION": 2.43,
      "REPITENCIA": 2.86
    },
    {
      "ANO": 2019,
      "DEPARTAMENTO": "Departamento K",
      "COBERTURA_NETA": 69.3,
      "DESERCION": 3.38,
      "REPITENCIA": 2.19
    },
    {
      "ANO": 2019,
      "DEPARTAMENTO": "Departamento L",
      "COBERTURA_NETA": 71.7,
      "DESERCION": 2.48,
      "REPITENCIA": 3.4
    },
    {
      "ANO": 2019,
      "DEPARTAMENTO": "Departamento M",
      "COBERTURA_NETA": 73.2,
      "DESERCION": 3.78,
      "REPITENCIA": 2.86
    },
    {
      "ANO": 2019,
      "DEPARTAMENTO": "Departamento N",
      "COBERTURA_NETA": 73.8,
      "DESERCION": 3.63,
      "REPITENCIA": 3.29
    },
    {
      "ANO": 2019,
      "DEPARTAMENTO": "Departamento O",
      "COBERTURA_NETA": 76.0,
      "DESERCION": 3.38,
      "REPITENCIA": 3.31
    },
    {
      "ANO": 2019,
      "DEPARTAMENTO": "Departamento P",
      "COBERTURA_NETA": 76.9,
      "DESERCION": 3.07,
      "REPITENCIA": 2.81
    },
    {
      "ANO": 2019,
      "DEPARTAMENTO": "Departamento Q",
      "COBERTURA_NETA": 77.3,
      "DESERCION": 2.45,
      "REPITENCIA": 2.26
    },
    {
      "ANO": 2019,
      "DEPARTAMENTO": "Departamento R",
      "COBERTURA_NETA": 80.2,
      "DESERCION": 3.12,
      "REPITENCIA": 3.17
    },
    {
      "ANO": 2019,
      "DEPARTAMENTO": "Departamento S",
      "COBERTURA_NETA": 80.8,
      "DESERCION": 2.71,
      "REPITENCIA": 2.47
    },
    {
      "ANO": 2019,
      "DEPARTAMENTO": "Departamento T",
      "COBERTURA_NETA": 82.1,
      "DESERCION": 3.35,
      "REPITENCIA": 2.88
    },
    {
      "ANO": 2019,
      "DEPARTAMENTO": "Departamento U",
      "COBERTURA_NETA": 83.0,
      "DESERCION": 3.19,
      "REPITENCIA": 2.52
    },
    {
      "ANO": 2019,
      "DEPARTAMENTO": "Departamento V",
      "COBERTURA_NETA": 84.9,
      "DESERCION": 3.11,
      "REPITENCIA": 3.0
    },
    {
      "ANO": 2019,
      "DEPARTAMENTO": "Departamento W",
      "COBERTURA_NETA": 87.0,
      "DESERCION": 3.85,
      "REPITENCIA": 2.2
    },
    {
      "ANO": 2019,
      "DEPARTAMENTO": "Departamento X",
      "COBERTURA_NETA": 87.0,
      "DESERCION": 3.93,
      "REPITENCIA": 2.53
    },
    {
      "ANO": 2019,
      "DEPARTAMENTO": "Departamento Y",
      "COBERTURA_NETA": 89.7,
      "DESERCION": 3.88,
      "REPITENCIA": 3.46
    },
    {
      "ANO": 2019,
      "DEPARTAMENTO": "Departamento Z",
      "COBERTURA_NETA": 91.4,
      "DESERCION": 3.1,
      "REPITENCIA": 2.97
    },
    {
      "ANO": 2019,
      "DEPARTAMENTO": "Departamento [",
      "COBERTURA_NETA": 91.3,
      "DESERCION": 3.14,
      "REPITENCIA": 3.55
    },
    {
      "ANO": 2019,
      "DEPARTAMENTO": "Departamento \\",
      "COBERTURA_NETA": 93.8,
      "DESERCION": 3.24,
      "REPITENCIA": 2.99
    },
    {
      "ANO": 2019,
      "DEPARTAMENTO": "Departamento ]",
      "COBERTURA_NETA": 95.7,
      "DESERCION": 3.04,
      "REPITENCIA": 2.67
    },
    {
      "ANO": 2019,
      "DEPARTAMENTO": "Departamento ^",
      "COBERTURA_NETA": 96.8,
      "DESERCION": 4.25,
      "REPITENCIA": 3.11
    },
    {
      "ANO": 2019,
      "DEPARTAMENTO": "Departamento _",
      "COBERTURA_NETA": 98.3,
      "DESERCION": 4.07,
      "REPITENCIA": 3.13
    },
    {
      "ANO": 2019,
      "DEPARTAMENTO": "Departamento `",
      "COBERTURA_NETA": 99.1,
      "DESERCION": 3.85,
      "REPITENCIA": 2.74
    },
    {
      "ANO": 2019,
      "DEPARTAMENTO": "Departamento a",
      "COBERTURA_NETA": 100.2,
      "DESERCION": 3.17,
      "REPITENCIA": 2.37
    },
    {
      "ANO": 2020,
      "DEPARTAMENTO": "Departamento A",
      "COBERTURA_NETA": 55.1,
      "DESERCION": 4.07,
      "REPITENCIA": 6.53
    },
    {
      "ANO": 2020,
      "DEPARTAMENTO": "Departamento B",
      "COBERTURA_NETA": 56.6,
      "DESERCION": 2.13,
      "REPITENCIA": 5.92
    },
    {
      "ANO": 2020,
      "DEPARTAMENTO": "Departamento C",
      "COBERTURA_NETA": 59.2,
      "DESERCION": 2.04,
      "REPITENCIA": 6.96
    },
    {
      "ANO": 2020,
      "DEPARTAMENTO": "Departamento D",
      "COBERTURA_NETA": 60.6,
      "DESERCION": 3.92,
      "REPITENCIA": 5.86
    },
    {
      "ANO": 2020,
      "DEPARTAMENTO": "Departamento E",
      "COBERTURA_NETA": 61.0,
      "DESERCION": 3.64,
      "REPITENCIA": 6.0
    },
    {
      "ANO": 2020,
      "DEPARTAMENTO": "Departamento F",
      "COBERTURA_NETA": 62.5,
      "DESERCION": 2.19,
      "REPITENCIA": 7.05
    },
    {
      "ANO": 2020,
      "DEPARTAMENTO": "Departamento G",
      "COBERTURA_NETA": 64.7,
      "DESERCION": 3.74,
      "REPITENCIA": 6.05
    },
    {
      "ANO": 2020,
      "DEPARTAMENTO": "Departamento H",
      "COBERTURA_NETA": 65.4,
      "DESERCION": 2.79,
      "REPITENCIA": 6.81
    },
    {
      "ANO": 2020,
      "DEPARTAMENTO": "Departamento I",
      "COBERTURA_NETA": 66.4,
      "DESERCION": 2.87,
      "REPITENCIA": 6.23
    },
    {
      "ANO": 2020,
      "DEPARTAMENTO": "Departamento J",
      "COBERTURA_NETA": 68.8,
      "DESERCION": 2.88,
      "REPITENCIA": 6.6
    },
    {
      "ANO": 2020,
      "DEPARTAMENTO": "Departamento K",
      "COBERTURA_NETA": 69.3,
      "DESERCION": 3.74,
      "REPITENCIA": 6.5
    },
    {
      "ANO": 2020,
      "DEPARTAMENTO": "Departamento L",
      "COBERTURA_NETA": 71.8,
      "DESERCION": 2.68,
      "REPITENCIA": 7.22
    },
    {
      "ANO": 2020,
      "DEPARTAMENTO": "Departamento M",
      "COBERTURA_NETA": 73.5,
      "DESERCION": 2.91,
      "REPITENCIA": 6.22
    },
    {
      "ANO": 2020,
      "DEPARTAMENTO": "Departamento N",
      "COBERTURA_NETA": 73.7,
      "DESERCION": 3.07,
      "REPITENCIA": 7.25
    },
    {
      "ANO": 2020,
      "DEPARTAMENTO": "Departamento O",
      "COBERTURA_NETA": 76.0,
      "DESERCION": 3.72,
      "REPITENCIA": 6.01
    },
    {
      "ANO": 2020,
      "DEPARTAMENTO": "Departamento P",
      "COBERTURA_NETA": 76.2,
      "DESERCION": 3.34,
      "REPITENCIA": 7.11
    },
    {
      "ANO": 2020,
      "DEPARTAMENTO": "Departamento Q",
      "COBERTURA_NETA": 78.2,
      "DESERCION": 2.05,
      "REPITENCIA": 7.07
    },
    {
      "ANO": 2020,
      "DEPARTAMENTO": "Departamento R",
      "COBERTURA_NETA": 80.2,
      "DESERCION": 2.48,
      "REPITENCIA": 6.94
    },
    {
      "ANO": 2020,
      "DEPARTAMENTO": "Departamento S",
      "COBERTURA_NETA": 80.5,
      "DESERCION": 3.97,
      "REPITENCIA": 6.02
    },
    {
      "ANO": 2020,
      "DEPARTAMENTO": "Departamento T",
      "COBERTURA_NETA": 82.2,
      "DESERCION": 4.07,
      "REPITENCIA": 6.13
    },
    {
      "ANO": 2020,
      "DEPARTAMENTO": "Departamento U",
      "COBERTURA_NETA": 83.6,
      "DESERCION": 2.64,
      "REPITENCIA": 5.84
    },
    {
      "ANO": 2020,
      "DEPARTAMENTO": "Departamento V",
      "COBERTURA_NETA": 84.2,
      "DESERCION": 3.0,
      "REPITENCIA": 6.15
    },
    {
      "ANO": 2020,
      "DEPARTAMENTO": "Departamento W",
      "COBERTURA_NETA": 87.5,
      "DESERCION": 2.7,
      "REPITENCIA": 5.84
    },
    {
      "ANO": 2020,
      "DEPARTAMENTO": "Departamento X",
      "COBERTURA_NETA": 88.8,
      "DESERCION": 3.81,
      "REPITENCIA": 6.77
    },
    {
      "ANO": 2020,
      "DEPARTAMENTO": "Departamento Y",
      "COBERTURA_NETA": 89.9,
      "DESERCION": 2.13,
      "REPITENCIA": 6.23
    },
    {
      "ANO": 2020,
      "DEPARTAMENTO": "Departamento Z",
      "COBERTURA_NETA": 91.4,
      "DESERCION": 3.47,
      "REPITENCIA": 6.01
    },
    {
      "ANO": 2020,
      "DEPARTAMENTO": "Departamento [",
      "COBERTURA_NETA": 92.5,
      "DESERCION": 2.88,
      "REPITENCIA": 5.81
    },
    {
      "ANO": 2020,
      "DEPARTAMENTO": "Departamento \\",
      "COBERTURA_NETA": 92.7,
      "DESERCION": 2.41,
      "REPITENCIA": 7.05
    },
    {
      "ANO": 2020,
      "DEPARTAMENTO": "Departamento ]",
      "COBERTURA_NETA": 95.0,
      "DESERCION": 3.55,
      "REPITENCIA": 6.59
    },
    {
      "ANO": 2020,
      "DEPARTAMENTO": "Departamento ^",
      "COBERTURA_NETA": 95.5,
      "DESERCION": 2.49,
      "REPITENCIA": 6.25
    },
    {
      "ANO": 2020,
      "DEPARTAMENTO": "Departamento _",
      "COBERTURA_NETA": 96.8,
      "DESERCION": 2.81,
      "REPITENCIA": 6.99
    },
    {
      "ANO": 2020,
      "DEPARTAMENTO": "Departamento `",
      "COBERTURA_NETA": 99.0,
      "DESERCION": 2.07,
      "REPITENCIA": 7.16
    },
    {
      "ANO": 2020,
      "DEPARTAMENTO": "Departamento a",
      "COBERTURA_NETA": 100.7,
      "DESERCION": 1.84,
      "REPITENCIA": 6.57
    },
    {
      "ANO": 2021,
      "DEPARTAMENTO": "Departamento A",
      "COBERTURA_NETA": 55.3,
      "DESERCION": 3.34,
      "REPITENCIA": 5.94
    },
    {
      "ANO": 2021,
      "DEPARTAMENTO": "Departamento B",
      "COBERTURA_NETA": 57.4,
      "DESERCION": 3.58,
      "REPITENCIA": 5.92
    },
    {
      "ANO": 2021,
      "DEPARTAMENTO": "Departamento C",
      "COBERTURA_NETA": 58.9,
      "DESERCION": 3.21,
      "REPITENCIA": 6.76
    },
    {
      "ANO": 2021,
      "DEPARTAMENTO": "Departamento D",
      "COBERTURA_NETA": 59.1,
      "DESERCION": 4.26,
      "REPITENCIA": 6.06
    },
    {
      "ANO": 2021,
      "DEPARTAMENTO": "Departamento E",
      "COBERTURA_NETA": 62.4,
      "DESERCION": 4.33,
      "REPITENCIA": 5.89
    },
    {
      "ANO": 2021,
      "DEPARTAMENTO": "Departamento F",
      "COBERTURA_NETA": 62.7,
      "DESERCION": 4.53,
      "REPITENCIA": 6.77
    },
    {
      "ANO": 2021,
      "DEPARTAMENTO": "Departamento G",
      "COBERTURA_NETA": 63.7,
      "DESERCION": 3.04,
      "REPITENCIA": 6.48
    },
    {
      "ANO": 2021,
      "DEPARTAMENTO": "Departamento H",
      "COBERTURA_NETA": 65.3,
      "DESERCION": 4.76,
      "REPITENCIA": 6.24
    },
    {
      "ANO": 2021,
      "DEPARTAMENTO": "Departamento I",
      "COBERTURA_NETA": 67.5,
      "DESERCION": 4.76,
      "REPITENCIA": 5.8
    },
    {
      "ANO": 2021,
      "DEPARTAMENTO": "Departamento J",
      "COBERTURA_NETA": 67.5,
      "DESERCION": 4.31,
      "REPITENCIA": 6.52
    },
    {
      "ANO": 2021,
      "DEPARTAMENTO": "Departamento K",
      "COBERTURA_NETA": 69.2,
      "DESERCION": 4.87,
      "REPITENCIA": 6.0
    },
    {
      "ANO": 2021,
      "DEPARTAMENTO": "Departamento L",
      "COBERTURA_NETA": 71.6,
      "DESERCION": 4.52,
      "REPITENCIA": 6.52
    },
    {
      "ANO": 2021,
      "DEPARTAMENTO": "Departamento M",
      "COBERTURA_NETA": 71.7,
      "DESERCION": 4.86,
      "REPITENCIA": 5.99
    },
    {
      "ANO": 2021,
      "DEPARTAMENTO": "Departamento N",
      "COBERTURA_NETA": 73.6,
      "DESERCION": 3.11,
      "REPITENCIA": 5.6
    },
    {
      "ANO": 2021,
      "DEPARTAMENTO": "Departamento O",
      "COBERTURA_NETA": 74.5,
      "DESERCION": 5.24,
      "REPITENCIA": 6.07
    },
    {
      "ANO": 2021,
      "DEPARTAMENTO": "Departamento P",
      "COBERTURA_NETA": 77.8,
      "DESERCION": 4.3,
      "REPITENCIA": 5.68
    },
    {
      "ANO": 2021,
      "DEPARTAMENTO": "Departamento Q",
      "COBERTURA_NETA": 78.7,
      "DESERCION": 3.46,
      "REPITENCIA": 5.84
    },
    {
      "ANO": 2021,
      "DEPARTAMENTO": "Departamento R",
      "COBERTURA_NETA": 80.2,
      "DESERCION": 5.08,
      "REPITENCIA": 5.8
    },
    {
      "ANO": 2021,
      "DEPARTAMENTO": "Departamento S",
      "COBERTURA_NETA": 80.2,
      "DESERCION": 3.88,
      "REPITENCIA": 6.63
    },
    {
      "ANO": 2021,
      "DEPARTAMENTO": "Departamento T",
      "COBERTURA_NETA": 82.9,
      "DESERCION": 5.15,
      "REPITENCIA": 5.88
    },
    {
      "ANO": 2021,
      "DEPARTAMENTO": "Departamento U",
      "COBERTURA_NETA": 84.7,
      "DESERCION": 4.19,
      "REPITENCIA": 6.05
    },
    {
      "ANO": 2021,
      "DEPARTAMENTO": "Departamento V",
      "COBERTURA_NETA": 86.0,
      "DESERCION": 4.25,
      "REPITENCIA": 6.5
    },
    {
      "ANO": 2021,
      "DEPARTAMENTO": "Departamento W",
      "COBERTURA_NETA": 87.1,
      "DESERCION": 3.19,
      "REPITENCIA": 6.2
    },
    {
      "ANO": 2021,
      "DEPARTAMENTO": "Departamento X",
      "COBERTURA_NETA": 88.6,
      "DESERCION": 4.31,
      "REPITENCIA": 5.78
    },
    {
      "ANO": 2021,
      "DEPARTAMENTO": "Departamento Y",
      "COBERTURA_NETA": 88.6,
      "DESERCION": 4.59,
      "REPITENCIA": 5.76
    },
    {
      "ANO": 2021,
      "DEPARTAMENTO": "Departamento Z",
      "COBERTURA_NETA": 91.0,
      "DESERCION": 4.02,
      "REPITENCIA": 6.33
    },
    {
      "ANO": 2021,
      "DEPARTAMENTO": "Departamento [",
      "COBERTURA_NETA": 91.9,
      "DESERCION": 3.1,
      "REPITENCIA": 6.61
    },
    {
      "ANO": 2021,
      "DEPARTAMENTO": "Departamento \\",
      "COBERTURA_NETA": 93.3,
      "DESERCION": 5.4,
      "REPITENCIA": 5.71
    },
    {
      "ANO": 2021,
      "DEPARTAMENTO": "Departamento ]",
      "COBERTURA_NETA": 96.0,
      "DESERCION": 5.27,
      "REPITENCIA": 5.41
    },
    {
      "ANO": 2021,
      "DEPARTAMENTO": "Departamento ^",
      "COBERTURA_NETA": 96.7,
      "DESERCION": 3.87,
      "REPITENCIA": 6.5
    },
    {
      "ANO": 2021,
      "DEPARTAMENTO": "Departamento _",
      "COBERTURA_NETA": 98.2,
      "DESERCION": 5.29,
      "REPITENCIA": 5.51
    },
    {
      "ANO": 2021,
      "DEPARTAMENTO": "Departamento `",
      "COBERTURA_NETA": 99.4,
      "DESERCION": 4.88,
      "REPITENCIA": 5.35
    },
    {
      "ANO": 2021,
      "DEPARTAMENTO": "Departamento a",
      "COBERTURA_NETA": 99.7,
      "DESERCION": 4.87,
      "REPITENCIA": 5.85
    },
    {
      "ANO": 2022,
      "DEPARTAMENTO": "Departamento A",
      "COBERTURA_NETA": 55.6,
      "DESERCION": 4.86,
      "REPITENCIA": 7.91
    },
    {
      "ANO": 2022,
      "DEPARTAMENTO": "Departamento B",
      "COBERTURA_NETA": 57.6,
      "DESERCION": 5.78,
      "REPITENCIA": 7.56
    },
    {
      "ANO": 2022,
      "DEPARTAMENTO": "Departamento C",
      "COBERTURA_NETA": 59.2,
      "DESERCION": 4.88,
      "REPITENCIA": 7.79
    },
    {
      "ANO": 2022,
      "DEPARTAMENTO": "Departamento D",
      "COBERTURA_NETA": 59.9,
      "DESERCION": 5.06,
      "REPITENCIA": 7.37
    },
    {
      "ANO": 2022,
      "DEPARTAMENTO": "Departamento E",
      "COBERTURA_NETA": 60.7,
      "DESERCION": 5.27,
      "REPITENCIA": 7.75
    },
    {
      "ANO": 2022,
      "DEPARTAMENTO": "Departamento F",
      "COBERTURA_NETA": 62.7,
      "DESERCION": 4.85,
      "REPITENCIA": 7.39
    },
    {
      "ANO": 2022,
      "DEPARTAMENTO": "Departamento G",
      "COBERTURA_NETA": 63.8,
      "DESERCION": 4.57,
      "REPITENCIA": 8.49
    },
    {
      "ANO": 2022,
      "DEPARTAMENTO": "Departamento H",
      "COBERTURA_NETA": 65.3,
      "DESERCION": 5.7,
      "REPITENCIA": 7.74
    },
    {
      "ANO": 2022,
      "DEPARTAMENTO": "Departamento I",
      "COBERTURA_NETA": 66.3,
      "DESERCION": 5.55,
      "REPITENCIA": 7.68
    },
    {
      "ANO": 2022,
      "DEPARTAMENTO": "Departamento J",
      "COBERTURA_NETA": 69.3,
      "DESERCION": 4.57,
      "REPITENCIA": 7.13
    },
    {
      "ANO": 2022,
      "DEPARTAMENTO": "Departamento K",
      "COBERTURA_NETA": 70.2,
      "DESERCION": 5.53,
      "REPITENCIA": 7.48
    },
    {
      "ANO": 2022,
      "DEPARTAMENTO": "Departamento L",
      "COBERTURA_NETA": 71.0,
      "DESERCION": 3.66,
      "REPITENCIA": 7.81
    },
    {
      "ANO": 2022,
      "DEPARTAMENTO": "Departamento M",
      "COBERTURA_NETA": 73.5,
      "DESERCION": 5.54,
      "REPITENCIA": 8.07
    },
    {
      "ANO": 2022,
      "DEPARTAMENTO": "Departamento N",
      "COBERTURA_NETA": 74.9,
      "DESERCION": 5.03,
      "REPITENCIA": 8.19
    },
    {
      "ANO": 2022,
      "DEPARTAMENTO": "Departamento O",
      "COBERTURA_NETA": 75.5,
      "DESERCION": 3.79,
      "REPITENCIA": 7.3
    },
    {
      "ANO": 2022,
      "DEPARTAMENTO": "Departamento P",
      "COBERTURA_NETA": 76.2,
      "DESERCION": 5.4,
      "REPITENCIA": 7.04
    },
    {
      "ANO": 2022,
      "DEPARTAMENTO": "Departamento Q",
      "COBERTURA_NETA": 78.4,
      "DESERCION": 4.39,
      "REPITENCIA": 8.21
    },
    {
      "ANO": 2022,
      "DEPARTAMENTO": "Departamento R",
      "COBERTURA_NETA": 79.8,
      "DESERCION": 4.97,
      "REPITENCIA": 7.13
    },
    {
      "ANO": 2022,
      "DEPARTAMENTO": "Departamento S",
      "COBERTURA_NETA": 80.7,
      "DESERCION": 5.9,
      "REPITENCIA": 8.08
    },
    {
      "ANO": 2022,
      "DEPARTAMENTO": "Departamento T",
      "COBERTURA_NETA": 82.5,
      "DESERCION": 5.35,
      "REPITENCIA": 8.24
    },
    {
      "ANO": 2022,
      "DEPARTAMENTO": "Departamento U",
      "COBERTURA_NETA": 83.0,
      "DESERCION": 5.83,
      "REPITENCIA": 7.96
    },
    {
      "ANO": 2022,
      "DEPARTAMENTO": "Departamento V",
      "COBERTURA_NETA": 85.2,
      "DESERCION": 5.13,
      "REPITENCIA": 7.52
    },
    {
      "ANO": 2022,
      "DEPARTAMENTO": "Departamento W",
      "COBERTURA_NETA": 87.4,
      "DESERCION": 5.37,
      "REPITENCIA": 7.96
    },
    {
      "ANO": 2022,
      "DEPARTAMENTO": "Departamento X",
      "COBERTURA_NETA": 87.4,
      "DESERCION": 5.82,
      "REPITENCIA": 7.65
    },
    {
      "ANO": 2022,
      "DEPARTAMENTO": "Departamento Y",
      "COBERTURA_NETA": 90.3,
      "DESERCION": 3.63,
      "REPITENCIA": 7.19
    },
    {
      "ANO": 2022,
      "DEPARTAMENTO": "Departamento Z",
      "COBERTURA_NETA": 90.2,
      "DESERCION": 3.9,
      "REPITENCIA": 7.48
    },
    {
      "ANO": 2022,
      "DEPARTAMENTO": "Departamento [",
      "COBERTURA_NETA": 92.7,
      "DESERCION": 4.33,
      "REPITENCIA": 8.41
    },
    {
      "ANO": 2022,
      "DEPARTAMENTO": "Departamento \\",
      "COBERTURA_NETA": 94.5,
      "DESERCION": 5.53,
      "REPITENCIA": 7.38
    },
    {
      "ANO": 2022,
      "DEPARTAMENTO": "Departamento ]",
      "COBERTURA_NETA": 95.4,
      "DESERCION": 4.82,
      "REPITENCIA": 7.19
    },
    {
      "ANO": 2022,
      "DEPARTAMENTO": "Departamento ^",
      "COBERTURA_NETA": 96.1,
      "DESERCION": 4.78,
      "REPITENCIA": 7.75
    },
    {
      "ANO": 2022,
      "DEPARTAMENTO": "Departamento _",
      "COBERTURA_NETA": 97.2,
      "DESERCION": 5.76,
      "REPITENCIA": 7.23
    },
    {
      "ANO": 2022,
      "DEPARTAMENTO": "Departamento `",
      "COBERTURA_NETA": 99.6,
      "DESERCION": 5.23,
      "REPITENCIA": 7.91
    },
    {
      "ANO": 2022,
      "DEPARTAMENTO": "Departamento a",
      "COBERTURA_NETA": 101.4,
      "DESERCION": 4.85,
      "REPITENCIA": 8.24
    },
    {
      "ANO": 2023,
      "DEPARTAMENTO": "Departamento A",
      "COBERTURA_NETA": 55.0,
      "DESERCION": 3.21,
      "REPITENCIA": 10.66
    },
    {
      "ANO": 2023,
      "DEPARTAMENTO": "Departamento B",
      "COBERTURA_NETA": 57.5,
      "DESERCION": 4.66,
      "REPITENCIA": 10.85
    },
    {
      "ANO": 2023,
      "DEPARTAMENTO": "Departamento C",
      "COBERTURA_NETA": 58.6,
      "DESERCION": 4.63,
      "REPITENCIA": 10.45
    },
    {
      "ANO": 2023,
      "DEPARTAMENTO": "Departamento D",
      "COBERTURA_NETA": 60.4,
      "DESERCION": 3.8,
      "REPITENCIA": 11.13
    },
    {
      "ANO": 2023,
      "DEPARTAMENTO": "Departamento E",
      "COBERTURA_NETA": 61.5,
      "DESERCION": 5.03,
      "REPITENCIA": 10.73
    },
    {
      "ANO": 2023,
      "DEPARTAMENTO": "Departamento F",
      "COBERTURA_NETA": 62.6,
      "DESERCION": 3.28,
      "REPITENCIA": 9.79
    },
    {
      "ANO": 2023,
      "DEPARTAMENTO": "Departamento G",
      "COBERTURA_NETA": 64.2,
      "DESERCION": 4.26,
      "REPITENCIA": 10.01
    },
    {
      "ANO": 2023,
      "DEPARTAMENTO": "Departamento H",
      "COBERTURA_NETA": 66.0,
      "DESERCION": 3.85,
      "REPITENCIA": 10.78
    },
    {
      "ANO": 2023,
      "DEPARTAMENTO": "Departamento I",
      "COBERTURA_NETA": 67.6,
      "DESERCION": 5.17,
      "REPITENCIA": 11.16
    },
    {
      "ANO": 2023,
      "DEPARTAMENTO": "Departamento J",
      "COBERTURA_NETA": 67.8,
      "DESERCION": 3.99,
      "REPITENCIA": 10.54
    },
    {
      "ANO": 2023,
      "DEPARTAMENTO": "Departamento K",
      "COBERTURA_NETA": 69.6,
      "DESERCION": 4.22,
      "REPITENCIA": 10.1
    },
    {
      "ANO": 2023,
      "DEPARTAMENTO": "Departamento L",
      "COBERTURA_NETA": 70.9,
      "DESERCION": 3.33,
      "REPITENCIA": 10.14
    },
    {
      "ANO": 2023,
      "DEPARTAMENTO": "Departamento M",
      "COBERTURA_NETA": 72.5,
      "DESERCION": 4.58,
      "REPITENCIA": 10.07
    },
    {
      "ANO": 2023,
      "DEPARTAMENTO": "Departamento N",
      "COBERTURA_NETA": 74.9,
      "DESERCION": 3.48,
      "REPITENCIA": 10.19
    },
    {
      "ANO": 2023,
      "DEPARTAMENTO": "Departamento O",
      "COBERTURA_NETA": 75.7,
      "DESERCION": 3.85,
      "REPITENCIA": 10.84
    },
    {
      "ANO": 2023,
      "DEPARTAMENTO": "Departamento P",
      "COBERTURA_NETA": 77.0,
      "DESERCION": 4.34,
      "REPITENCIA": 10.45
    },
    {
      "ANO": 2023,
      "DEPARTAMENTO": "Departamento Q",
      "COBERTURA_NETA": 78.0,
      "DESERCION": 3.16,
      "REPITENCIA": 11.12
    },
    {
      "ANO": 2023,
      "DEPARTAMENTO": "Departamento R",
      "COBERTURA_NETA": 79.8,
      "DESERCION": 5.42,
      "REPITENCIA": 10.02
    },
    {
      "ANO": 2023,
      "DEPARTAMENTO": "Departamento S",
      "COBERTURA_NETA": 80.9,
      "DESERCION": 3.22,
      "REPITENCIA": 10.44
    },
    {
      "ANO": 2023,
      "DEPARTAMENTO": "Departamento T",
      "COBERTURA_NETA": 83.3,
      "DESERCION": 4.67,
      "REPITENCIA": 10.41
    },
    {
      "ANO": 2023,
      "DEPARTAMENTO": "Departamento U",
      "COBERTURA_NETA": 84.0,
      "DESERCION": 5.13,
      "REPITENCIA": 10.35
    },
    {
      "ANO": 2023,
      "DEPARTAMENTO": "Departamento V",
      "COBERTURA_NETA": 86.1,
      "DESERCION": 4.85,
      "REPITENCIA": 10.85
    },
    {
      "ANO": 2023,
      "DEPARTAMENTO": "Departamento W",
      "COBERTURA_NETA": 86.5,
      "DESERCION": 4.06,
      "REPITENCIA": 10.56
    },
    {
      "ANO": 2023,
      "DEPARTAMENTO": "Departamento X",
      "COBERTURA_NETA": 87.5,
      "DESERCION": 4.43,
      "REPITENCIA": 9.81
    },
    {
      "ANO": 2023,
      "DEPARTAMENTO": "Departamento Y",
      "COBERTURA_NETA": 89.6,
      "DESERCION": 4.93,
      "REPITENCIA": 10.12
    },
    {
      "ANO": 2023,
      "DEPARTAMENTO": "Departamento Z",
      "COBERTURA_NETA": 91.9,
      "DESERCION": 4.73,
      "REPITENCIA": 9.88
    },
    {
      "ANO": 2023,
      "DEPARTAMENTO": "Departamento [",
      "COBERTURA_NETA": 93.3,
      "DESERCION": 4.05,
      "REPITENCIA": 10.89
    },
    {
      "ANO": 2023,
      "DEPARTAMENTO": "Departamento \\",
      "COBERTURA_NETA": 93.4,
      "DESERCION": 5.35,
      "REPITENCIA": 10.83
    },
    {
      "ANO": 2023,
      "DEPARTAMENTO": "Departamento ]",
      "COBERTURA_NETA": 94.6,
      "DESERCION": 4.32,
      "REPITENCIA": 10.45
    },
    {
      "ANO": 2023,
      "DEPARTAMENTO": "Departamento ^",
      "COBERTURA_NETA": 95.7,
      "DESERCION": 3.43,
      "REPITENCIA": 10.2
    },
    {
      "ANO": 2023,
      "DEPARTAMENTO": "Departamento _",
      "COBERTURA_NETA": 97.9,
      "DESERCION": 4.2,
      "REPITENCIA": 10.61
    },
    {
      "ANO": 2023,
      "DEPARTAMENTO": "Departamento `",
      "COBERTURA_NETA": 99.4,
      "DESERCION": 3.89,
      "REPITENCIA": 10.62
    },
    {
      "ANO": 2023,
      "DEPARTAMENTO": "Departamento a",
      "COBERTURA_NETA": 100.1,
      "DESERCION": 5.48,
      "REPITENCIA": 10.81
    },
    {
      "ANO": 2024,
      "DEPARTAMENTO": "Departamento A",
      "COBERTURA_NETA": 55.6,
      "DESERCION": 3.71,
      "REPITENCIA": 10.44
    },
    {
      "ANO": 2024,
      "DEPARTAMENTO": "Departamento B",
      "COBERTURA_NETA": 57.5,
      "DESERCION": 4.6,
      "REPITENCIA": 9.65
    },
    {
      "ANO": 2024,
      "DEPARTAMENTO": "Departamento C",
      "COBERTURA_NETA": 59.5,
      "DESERCION": 3.78,
      "REPITENCIA": 10.21
    },
    {
      "ANO": 2024,
      "DEPARTAMENTO": "Departamento D",
      "COBERTURA_NETA": 61.2,
      "DESERCION": 4.3,
      "REPITENCIA": 10.4
    },
    {
      "ANO": 2024,
      "DEPARTAMENTO": "Departamento E",
      "COBERTURA_NETA": 62.1,
      "DESERCION": 4.55,
      "REPITENCIA": 9.24
    },
    {
      "ANO": 2024,
      "DEPARTAMENTO": "Departamento F",
      "COBERTURA_NETA": 63.0,
      "DESERCION": 5.22,
      "REPITENCIA": 10.37
    },
    {
      "ANO": 2024,
      "DEPARTAMENTO": "Departamento G",
      "COBERTURA_NETA": 65.0,
      "DESERCION": 4.29,
      "REPITENCIA": 10.28
    },
    {
      "ANO": 2024,
      "DEPARTAMENTO": "Departamento H",
      "COBERTURA_NETA": 66.0,
      "DESERCION": 3.31,
      "REPITENCIA": 10.14
    },
    {
      "ANO": 2024,
      "DEPARTAMENTO": "Departamento I",
      "COBERTURA_NETA": 67.5,
      "DESERCION": 4.92,
      "REPITENCIA": 9.42
    },
    {
      "ANO": 2024,
      "DEPARTAMENTO": "Departamento J",
      "COBERTURA_NETA": 69.0,
      "DESERCION": 2.98,
      "REPITENCIA": 10.62
    },
    {
      "ANO": 2024,
      "DEPARTAMENTO": "Departamento K",
      "COBERTURA_NETA": 69.3,
      "DESERCION": 2.95,
      "REPITENCIA": 9.67
    },
    {
      "ANO": 2024,
      "DEPARTAMENTO": "Departamento L",
      "COBERTURA_NETA": 70.7,
      "DESERCION": 4.56,
      "REPITENCIA": 9.82
    },
    {
      "ANO": 2024,
      "DEPARTAMENTO": "Departamento M",
      "COBERTURA_NETA": 73.4,
      "DESERCION": 5.11,
      "REPITENCIA": 10.51
    },
    {
      "ANO": 2024,
      "DEPARTAMENTO": "Departamento N",
      "COBERTURA_NETA": 74.7,
      "DESERCION": 3.05,
      "REPITENCIA": 9.41
    },
    {
      "ANO": 2024,
      "DEPARTAMENTO": "Departamento O",
      "COBERTURA_NETA": 75.1,
      "DESERCION": 3.68,
      "REPITENCIA": 10.19
    },
    {
      "ANO": 2024,
      "DEPARTAMENTO": "Departamento P",
      "COBERTURA_NETA": 77.1,
      "DESERCION": 3.65,
      "REPITENCIA": 9.46
    },
    {
      "ANO": 2024,
      "DEPARTAMENTO": "Departamento Q",
      "COBERTURA_NETA": 79.3,
      "DESERCION": 3.72,
      "REPITENCIA": 9.73
    },
    {
      "ANO": 2024,
      "DEPARTAMENTO": "Departamento R",
      "COBERTURA_NETA": 80.4,
      "DESERCION": 4.63,
      "REPITENCIA": 10.16
    },
    {
      "ANO": 2024,
      "DEPARTAMENTO": "Departamento S",
      "COBERTURA_NETA": 81.6,
      "DESERCION": 4.36,
      "REPITENCIA": 9.49
    },
    {
      "ANO": 2024,
      "DEPARTAMENTO": "Departamento T",
      "COBERTURA_NETA": 82.1,
      "DESERCION": 4.24,
      "REPITENCIA": 9.54
    },
    {
      "ANO": 2024,
      "DEPARTAMENTO": "Departamento U",
      "COBERTURA_NETA": 85.0,
      "DESERCION": 3.61,
      "REPITENCIA": 9.63
    },
    {
      "ANO": 2024,
      "DEPARTAMENTO": "Departamento V",
      "COBERTURA_NETA": 84.9,
      "DESERCION": 4.59,
      "REPITENCIA": 9.68
    },
    {
      "ANO": 2024,
      "DEPARTAMENTO": "Departamento W",
      "COBERTURA_NETA": 86.5,
      "DESERCION": 5.14,
      "REPITENCIA": 10.39
    },
    {
      "ANO": 2024,
      "DEPARTAMENTO": "Departamento X",
      "COBERTURA_NETA": 87.8,
      "DESERCION": 3.19,
      "REPITENCIA": 10.21
    },
    {
      "ANO": 2024,
      "DEPARTAMENTO": "Departamento Y",
      "COBERTURA_NETA": 89.4,
      "DESERCION": 5.25,
      "REPITENCIA": 10.43
    },
    {
      "ANO": 2024,
      "DEPARTAMENTO": "Departamento Z",
      "COBERTURA_NETA": 91.9,
      "DESERCION": 4.83,
      "REPITENCIA": 9.64
    },
    {
      "ANO": 2024,
      "DEPARTAMENTO": "Departamento [",
      "COBERTURA_NETA": 92.0,
      "DESERCION": 4.61,
      "REPITENCIA": 9.72
    },
    {
      "ANO": 2024,
      "DEPARTAMENTO": "Departamento \\",
      "COBERTURA_NETA": 93.7,
      "DESERCION": 3.52,
      "REPITENCIA": 9.92
    },
    {
      "ANO": 2024,
      "DEPARTAMENTO": "Departamento ]",
      "COBERTURA_NETA": 94.6,
      "DESERCION": 4.19,
      "REPITENCIA": 10.6
    },
    {
      "ANO": 2024,
      "DEPARTAMENTO": "Departamento ^",
      "COBERTURA_NETA": 97.0,
      "DESERCION": 3.23,
      "REPITENCIA": 10.12
    },
    {
      "ANO": 2024,
      "DEPARTAMENTO": "Departamento _",
      "COBERTURA_NETA": 98.2,
      "DESERCION": 3.48,
      "REPITENCIA": 10.2
    },
    {
      "ANO": 2024,
      "DEPARTAMENTO": "Departamento `",
      "COBERTURA_NETA": 99.5,
      "DESERCION": 4.43,
      "REPITENCIA": 9.28
    },
    {
      "ANO": 2024,
      "DEPARTAMENTO": "Departamento a",
      "COBERTURA_NETA": 100.7,
      "DESERCION": 4.62,
      "REPITENCIA": 9.35
    }
  ]
}